{
  "a_comp_cor_00": {
    "CumulativeVarianceExplained": 0.0452369924,
    "Mask": "combined",
    "Method": "aCompCor",
    "Retained": true,
    "SingularValue": 180.3981494254,
    "VarianceExplained": 0.0452369924
  },
  "a_comp_cor_01": {
    "CumulativeVarianceExplained": 0.0758189981,
    "Mask": "combined",
    "Method": "aCompCor",
    "Retained": true,
    "SingularValue": 148.326312213,
    "VarianceExplained": 0.0305820057
  },
  "a_comp_cor_02": {
    "CumulativeVarianceExplained": 0.099427769,
    "Mask": "combined",
    "Method": "aCompCor",
    "Retained": true,
    "SingularValue": 130.3232512009,
    "VarianceExplained": 0.0236087709
  },
  "a_comp_cor_03": {
    "CumulativeVarianceExplained": 0.1208978292,
    "Mask": "combined",
    "Method": "aCompCor",
    "Retained": true,
    "SingularValue": 124.2801725338,
    "VarianceExplained": 0.0214700602
  },
  "a_comp_cor_04": {
    "CumulativeVarianceExplained": 0.1382902999,
    "Mask": "combined",
    "Method": "aCompCor",
    "Retained": true,
    "SingularValue": 111.8576927326,
    "VarianceExplained": 0.0173924707
  },
  "a_comp_cor_05": {
    "CumulativeVarianceExplained": 0.1524589282,
    "Mask": "combined",
    "Method": "aCompCor",
    "Retained": true,
    "SingularValue": 100.9599486651,
    "VarianceExplained": 0.0141686283
  },
  "a_comp_cor_06": {
    "CumulativeVarianceExplained": 0.165512141,
    "Mask": "combined",
    "Method": "aCompCor",
    "Retained": true,
    "SingularValue": 96.9044956792,
    "VarianceExplained": 0.0130532128
  },
  "a_comp_cor_07": {
    "CumulativeVarianceExplained": 0.1771761173,
    "Mask": "combined",
    "Method": "aCompCor",
    "Retained": true,
    "SingularValue": 91.6027539868,
    "VarianceExplained": 0.0116639763
  },
  "a_comp_cor_08": {
    "CumulativeVarianceExplained": 0.1880564498,
    "Mask": "combined",
    "Method": "aCompCor",
    "Retained": true,
    "SingularValue": 88.4720926647,
    "VarianceExplained": 0.0108803325
  },
  "a_comp_cor_09": {
    "CumulativeVarianceExplained": 0.197811145,
    "Mask": "combined",
    "Method": "aCompCor",
    "Retained": true,
    "SingularValue": 83.7706857009,
    "VarianceExplained": 0.0097546953
  },
  "a_comp_cor_10": {
    "CumulativeVarianceExplained": 0.2072145246,
    "Mask": "combined",
    "Method": "aCompCor",
    "Retained": true,
    "SingularValue": 82.2483509062,
    "VarianceExplained": 0.0094033795
  },
  "a_comp_cor_11": {
    "CumulativeVarianceExplained": 0.2162684798,
    "Mask": "combined",
    "Method": "aCompCor",
    "Retained": true,
    "SingularValue": 80.7057333834,
    "VarianceExplained": 0.0090539552
  },
  "a_comp_cor_12": {
    "CumulativeVarianceExplained": 0.2249491101,
    "Mask": "combined",
    "Method": "aCompCor",
    "Retained": true,
    "SingularValue": 79.0243344736,
    "VarianceExplained": 0.0086806303
  },
  "a_comp_cor_13": {
    "CumulativeVarianceExplained": 0.233255729,
    "Mask": "combined",
    "Method": "aCompCor",
    "Retained": true,
    "SingularValue": 77.3031798557,
    "VarianceExplained": 0.0083066189
  },
  "a_comp_cor_14": {
    "CumulativeVarianceExplained": 0.2414565762,
    "Mask": "combined",
    "Method": "aCompCor",
    "Retained": true,
    "SingularValue": 76.8094362589,
    "VarianceExplained": 0.0082008472
  },
  "a_comp_cor_15": {
    "CumulativeVarianceExplained": 0.249343791,
    "Mask": "combined",
    "Method": "aCompCor",
    "Retained": true,
    "SingularValue": 75.3263717962,
    "VarianceExplained": 0.0078872147
  },
  "a_comp_cor_16": {
    "CumulativeVarianceExplained": 0.2570268705,
    "Mask": "combined",
    "Method": "aCompCor",
    "Retained": true,
    "SingularValue": 74.3451909209,
    "VarianceExplained": 0.0076830795
  },
  "a_comp_cor_17": {
    "CumulativeVarianceExplained": 0.2644401773,
    "Mask": "combined",
    "Method": "aCompCor",
    "Retained": true,
    "SingularValue": 73.0283023395,
    "VarianceExplained": 0.0074133068
  },
  "a_comp_cor_18": {
    "CumulativeVarianceExplained": 0.2718035504,
    "Mask": "combined",
    "Method": "aCompCor",
    "Retained": true,
    "SingularValue": 72.7819386543,
    "VarianceExplained": 0.0073633731
  },
  "a_comp_cor_19": {
    "CumulativeVarianceExplained": 0.2789643254,
    "Mask": "combined",
    "Method": "aCompCor",
    "Retained": true,
    "SingularValue": 71.7736829308,
    "VarianceExplained": 0.007160775
  },
  "a_comp_cor_20": {
    "CumulativeVarianceExplained": 0.2859258333,
    "Mask": "combined",
    "Method": "aCompCor",
    "Retained": true,
    "SingularValue": 70.7679923023,
    "VarianceExplained": 0.0069615078
  },
  "a_comp_cor_21": {
    "CumulativeVarianceExplained": 0.2926899939,
    "Mask": "combined",
    "Method": "aCompCor",
    "Retained": true,
    "SingularValue": 69.7577032709,
    "VarianceExplained": 0.0067641606
  },
  "a_comp_cor_22": {
    "CumulativeVarianceExplained": 0.2993077715,
    "Mask": "combined",
    "Method": "aCompCor",
    "Retained": true,
    "SingularValue": 68.9987623791,
    "VarianceExplained": 0.0066177776
  },
  "a_comp_cor_23": {
    "CumulativeVarianceExplained": 0.3057197104,
    "Mask": "combined",
    "Method": "aCompCor",
    "Retained": true,
    "SingularValue": 67.9172202365,
    "VarianceExplained": 0.0064119388
  },
  "a_comp_cor_24": {
    "CumulativeVarianceExplained": 0.3119438233,
    "Mask": "combined",
    "Method": "aCompCor",
    "Retained": true,
    "SingularValue": 66.915071736,
    "VarianceExplained": 0.0062241129
  },
  "a_comp_cor_25": {
    "CumulativeVarianceExplained": 0.3180961391,
    "Mask": "combined",
    "Method": "aCompCor",
    "Retained": true,
    "SingularValue": 66.5280093763,
    "VarianceExplained": 0.0061523159
  },
  "a_comp_cor_26": {
    "CumulativeVarianceExplained": 0.3241649388,
    "Mask": "combined",
    "Method": "aCompCor",
    "Retained": true,
    "SingularValue": 66.0749157764,
    "VarianceExplained": 0.0060687997
  },
  "a_comp_cor_27": {
    "CumulativeVarianceExplained": 0.3300836411,
    "Mask": "combined",
    "Method": "aCompCor",
    "Retained": true,
    "SingularValue": 65.2526964968,
    "VarianceExplained": 0.0059187023
  },
  "a_comp_cor_28": {
    "CumulativeVarianceExplained": 0.3359566863,
    "Mask": "combined",
    "Method": "aCompCor",
    "Retained": true,
    "SingularValue": 65.0005289615,
    "VarianceExplained": 0.0058730453
  },
  "a_comp_cor_29": {
    "CumulativeVarianceExplained": 0.3417635325,
    "Mask": "combined",
    "Method": "aCompCor",
    "Retained": true,
    "SingularValue": 64.6331581373,
    "VarianceExplained": 0.0058068462
  },
  "a_comp_cor_30": {
    "CumulativeVarianceExplained": 0.3474753256,
    "Mask": "combined",
    "Method": "aCompCor",
    "Retained": true,
    "SingularValue": 64.101980951,
    "VarianceExplained": 0.0057117931
  },
  "a_comp_cor_31": {
    "CumulativeVarianceExplained": 0.3531451909,
    "Mask": "combined",
    "Method": "aCompCor",
    "Retained": true,
    "SingularValue": 63.8662748078,
    "VarianceExplained": 0.0056698652
  },
  "a_comp_cor_32": {
    "CumulativeVarianceExplained": 0.3587087328,
    "Mask": "combined",
    "Method": "aCompCor",
    "Retained": true,
    "SingularValue": 63.2646193008,
    "VarianceExplained": 0.0055635419
  },
  "a_comp_cor_33": {
    "CumulativeVarianceExplained": 0.3641588967,
    "Mask": "combined",
    "Method": "aCompCor",
    "Retained": true,
    "SingularValue": 62.6166747822,
    "VarianceExplained": 0.005450164
  },
  "a_comp_cor_34": {
    "CumulativeVarianceExplained": 0.36959534,
    "Mask": "combined",
    "Method": "aCompCor",
    "Retained": true,
    "SingularValue": 62.5378069616,
    "VarianceExplained": 0.0054364433
  },
  "a_comp_cor_35": {
    "CumulativeVarianceExplained": 0.3750092267,
    "Mask": "combined",
    "Method": "aCompCor",
    "Retained": true,
    "SingularValue": 62.4079327448,
    "VarianceExplained": 0.0054138867
  },
  "a_comp_cor_36": {
    "CumulativeVarianceExplained": 0.3803319216,
    "Mask": "combined",
    "Method": "aCompCor",
    "Retained": true,
    "SingularValue": 61.8800996189,
    "VarianceExplained": 0.0053226949
  },
  "a_comp_cor_37": {
    "CumulativeVarianceExplained": 0.3855763204,
    "Mask": "combined",
    "Method": "aCompCor",
    "Retained": true,
    "SingularValue": 61.4232892762,
    "VarianceExplained": 0.0052443988
  },
  "a_comp_cor_38": {
    "CumulativeVarianceExplained": 0.3907387274,
    "Mask": "combined",
    "Method": "aCompCor",
    "Retained": true,
    "SingularValue": 60.9412472163,
    "VarianceExplained": 0.005162407
  },
  "a_comp_cor_39": {
    "CumulativeVarianceExplained": 0.3958791469,
    "Mask": "combined",
    "Method": "aCompCor",
    "Retained": true,
    "SingularValue": 60.8113295163,
    "VarianceExplained": 0.0051404195
  },
  "a_comp_cor_40": {
    "CumulativeVarianceExplained": 0.4009812935,
    "Mask": "combined",
    "Method": "aCompCor",
    "Retained": true,
    "SingularValue": 60.5845215373,
    "VarianceExplained": 0.0051021466
  },
  "a_comp_cor_41": {
    "CumulativeVarianceExplained": 0.4060397107,
    "Mask": "combined",
    "Method": "aCompCor",
    "Retained": true,
    "SingularValue": 60.3243345105,
    "VarianceExplained": 0.0050584172
  },
  "a_comp_cor_42": {
    "CumulativeVarianceExplained": 0.4110494983,
    "Mask": "combined",
    "Method": "aCompCor",
    "Retained": true,
    "SingularValue": 60.0336674345,
    "VarianceExplained": 0.0050097876
  },
  "a_comp_cor_43": {
    "CumulativeVarianceExplained": 0.4159570872,
    "Mask": "combined",
    "Method": "aCompCor",
    "Retained": true,
    "SingularValue": 59.4181741173,
    "VarianceExplained": 0.0049075888
  },
  "a_comp_cor_44": {
    "CumulativeVarianceExplained": 0.4208135924,
    "Mask": "combined",
    "Method": "aCompCor",
    "Retained": true,
    "SingularValue": 59.1081203242,
    "VarianceExplained": 0.0048565053
  },
  "a_comp_cor_45": {
    "CumulativeVarianceExplained": 0.425636213,
    "Mask": "combined",
    "Method": "aCompCor",
    "Retained": true,
    "SingularValue": 58.9015556552,
    "VarianceExplained": 0.0048226206
  },
  "a_comp_cor_46": {
    "CumulativeVarianceExplained": 0.4304323852,
    "Mask": "combined",
    "Method": "aCompCor",
    "Retained": true,
    "SingularValue": 58.7398181094,
    "VarianceExplained": 0.0047961721
  },
  "a_comp_cor_47": {
    "CumulativeVarianceExplained": 0.4351716532,
    "Mask": "combined",
    "Method": "aCompCor",
    "Retained": true,
    "SingularValue": 58.3903196522,
    "VarianceExplained": 0.004739268
  },
  "a_comp_cor_48": {
    "CumulativeVarianceExplained": 0.4398665583,
    "Mask": "combined",
    "Method": "aCompCor",
    "Retained": true,
    "SingularValue": 58.1163894711,
    "VarianceExplained": 0.0046949051
  },
  "a_comp_cor_49": {
    "CumulativeVarianceExplained": 0.4444625836,
    "Mask": "combined",
    "Method": "aCompCor",
    "Retained": true,
    "SingularValue": 57.5011354271,
    "VarianceExplained": 0.0045960253
  },
  "a_comp_cor_50": {
    "CumulativeVarianceExplained": 0.4490218726,
    "Mask": "combined",
    "Method": "aCompCor",
    "Retained": true,
    "SingularValue": 57.2708700639,
    "VarianceExplained": 0.0045592891
  },
  "a_comp_cor_51": {
    "CumulativeVarianceExplained": 0.4535641418,
    "Mask": "combined",
    "Method": "aCompCor",
    "Retained": true,
    "SingularValue": 57.163873418,
    "VarianceExplained": 0.0045422691
  },
  "a_comp_cor_52": {
    "CumulativeVarianceExplained": 0.4580623439,
    "Mask": "combined",
    "Method": "aCompCor",
    "Retained": true,
    "SingularValue": 56.885908306,
    "VarianceExplained": 0.0044982021
  },
  "a_comp_cor_53": {
    "CumulativeVarianceExplained": 0.4625509536,
    "Mask": "combined",
    "Method": "aCompCor",
    "Retained": true,
    "SingularValue": 56.8252216687,
    "VarianceExplained": 0.0044886097
  },
  "a_comp_cor_54": {
    "CumulativeVarianceExplained": 0.4670043225,
    "Mask": "combined",
    "Method": "aCompCor",
    "Retained": true,
    "SingularValue": 56.6017103498,
    "VarianceExplained": 0.0044533689
  },
  "a_comp_cor_55": {
    "CumulativeVarianceExplained": 0.4714290562,
    "Mask": "combined",
    "Method": "aCompCor",
    "Retained": true,
    "SingularValue": 56.4194417614,
    "VarianceExplained": 0.0044247337
  },
  "a_comp_cor_56": {
    "CumulativeVarianceExplained": 0.4757925461,
    "Mask": "combined",
    "Method": "aCompCor",
    "Retained": true,
    "SingularValue": 56.027623949,
    "VarianceExplained": 0.0043634899
  },
  "a_comp_cor_57": {
    "CumulativeVarianceExplained": 0.4801253829,
    "Mask": "combined",
    "Method": "aCompCor",
    "Retained": true,
    "SingularValue": 55.8304827199,
    "VarianceExplained": 0.0043328368
  },
  "a_comp_cor_58": {
    "CumulativeVarianceExplained": 0.4844288534,
    "Mask": "combined",
    "Method": "aCompCor",
    "Retained": true,
    "SingularValue": 55.6409621041,
    "VarianceExplained": 0.0043034705
  },
  "a_comp_cor_59": {
    "CumulativeVarianceExplained": 0.4887099838,
    "Mask": "combined",
    "Method": "aCompCor",
    "Retained": true,
    "SingularValue": 55.4963531435,
    "VarianceExplained": 0.0042811304
  },
  "a_comp_cor_60": {
    "CumulativeVarianceExplained": 0.4929305472,
    "Mask": "combined",
    "Method": "aCompCor",
    "Retained": true,
    "SingularValue": 55.102389616,
    "VarianceExplained": 0.0042205634
  },
  "a_comp_cor_61": {
    "CumulativeVarianceExplained": 0.4971111241,
    "Mask": "combined",
    "Method": "aCompCor",
    "Retained": true,
    "SingularValue": 54.8407421384,
    "VarianceExplained": 0.0041805769
  },
  "a_comp_cor_62": {
    "CumulativeVarianceExplained": 0.5012627851,
    "Mask": "combined",
    "Method": "aCompCor",
    "Retained": true,
    "SingularValue": 54.6507543205,
    "VarianceExplained": 0.004151661
  },
  "c_comp_cor_00": {
    "CumulativeVarianceExplained": 0.1405476892,
    "Mask": "CSF",
    "Method": "aCompCor",
    "Retained": true,
    "SingularValue": 89.9752571385,
    "VarianceExplained": 0.1405476892
  },
  "c_comp_cor_01": {
    "CumulativeVarianceExplained": 0.2448500062,
    "Mask": "CSF",
    "Method": "aCompCor",
    "Retained": true,
    "SingularValue": 77.510086167,
    "VarianceExplained": 0.104302317
  },
  "c_comp_cor_02": {
    "CumulativeVarianceExplained": 0.3197569126,
    "Mask": "CSF",
    "Method": "aCompCor",
    "Retained": true,
    "SingularValue": 65.6859026779,
    "VarianceExplained": 0.0749069064
  },
  "c_comp_cor_03": {
    "CumulativeVarianceExplained": 0.372191013,
    "Mask": "CSF",
    "Method": "aCompCor",
    "Retained": true,
    "SingularValue": 54.9563843816,
    "VarianceExplained": 0.0524341004
  },
  "c_comp_cor_04": {
    "CumulativeVarianceExplained": 0.4149401196,
    "Mask": "CSF",
    "Method": "aCompCor",
    "Retained": true,
    "SingularValue": 49.6220569807,
    "VarianceExplained": 0.0427491066
  },
  "c_comp_cor_05": {
    "CumulativeVarianceExplained": 0.4509820978,
    "Mask": "CSF",
    "Method": "aCompCor",
    "Retained": true,
    "SingularValue": 45.5633398893,
    "VarianceExplained": 0.0360419782
  },
  "c_comp_cor_06": {
    "CumulativeVarianceExplained": 0.4839483857,
    "Mask": "CSF",
    "Method": "aCompCor",
    "Retained": true,
    "SingularValue": 43.5758899564,
    "VarianceExplained": 0.0329662879
  },
  "c_comp_cor_07": {
    "CumulativeVarianceExplained": 0.5125490077,
    "Mask": "CSF",
    "Method": "aCompCor",
    "Retained": true,
    "SingularValue": 40.5881242027,
    "VarianceExplained": 0.028600622
  },
  "dropped_0": {
    "CumulativeVarianceExplained": 0.4938150704,
    "Mask": "Edge",
    "Method": "EdgeRegressor",
    "Retained": false,
    "SingularValue": 134.0644047989,
    "VarianceExplained": 0.0052269135
  },
  "dropped_1": {
    "CumulativeVarianceExplained": 0.4988860657,
    "Mask": "Edge",
    "Method": "EdgeRegressor",
    "Retained": false,
    "SingularValue": 132.049704131,
    "VarianceExplained": 0.0050709953
  },
  "dropped_10": {
    "CumulativeVarianceExplained": 0.5374582569,
    "Mask": "Edge",
    "Method": "EdgeRegressor",
    "Retained": false,
    "SingularValue": 114.0133876168,
    "VarianceExplained": 0.0037803329
  },
  "dropped_100": {
    "CumulativeVarianceExplained": 0.7592750872,
    "Mask": "Edge",
    "Method": "EdgeRegressor",
    "Retained": false,
    "SingularValue": 80.79312164,
    "VarianceExplained": 0.0018983099
  },
  "dropped_101": {
    "CumulativeVarianceExplained": 0.7611698697,
    "Mask": "Edge",
    "Method": "EdgeRegressor",
    "Retained": false,
    "SingularValue": 80.7180225888,
    "VarianceExplained": 0.0018947825
  },
  "dropped_102": {
    "CumulativeVarianceExplained": 0.7630543525,
    "Mask": "Edge",
    "Method": "EdgeRegressor",
    "Retained": false,
    "SingularValue": 80.4983391594,
    "VarianceExplained": 0.0018844828
  },
  "dropped_103": {
    "CumulativeVarianceExplained": 0.7649338328,
    "Mask": "Edge",
    "Method": "EdgeRegressor",
    "Retained": false,
    "SingularValue": 80.391423438,
    "VarianceExplained": 0.0018794803
  },
  "dropped_104": {
    "CumulativeVarianceExplained": 0.7668086872,
    "Mask": "Edge",
    "Method": "EdgeRegressor",
    "Retained": false,
    "SingularValue": 80.2924306175,
    "VarianceExplained": 0.0018748544
  },
  "dropped_105": {
    "CumulativeVarianceExplained": 0.7686777642,
    "Mask": "Edge",
    "Method": "EdgeRegressor",
    "Retained": false,
    "SingularValue": 80.1686231481,
    "VarianceExplained": 0.001869077
  },
  "dropped_106": {
    "CumulativeVarianceExplained": 0.7705400407,
    "Mask": "Edge",
    "Method": "EdgeRegressor",
    "Retained": false,
    "SingularValue": 80.0226458971,
    "VarianceExplained": 0.0018622765
  },
  "dropped_107": {
    "CumulativeVarianceExplained": 0.772395726,
    "Mask": "Edge",
    "Method": "EdgeRegressor",
    "Retained": false,
    "SingularValue": 79.8809091521,
    "VarianceExplained": 0.0018556854
  },
  "dropped_108": {
    "CumulativeVarianceExplained": 0.7742451956,
    "Mask": "Edge",
    "Method": "EdgeRegressor",
    "Retained": false,
    "SingularValue": 79.747012229,
    "VarianceExplained": 0.0018494695
  },
  "dropped_109": {
    "CumulativeVarianceExplained": 0.7760848649,
    "Mask": "Edge",
    "Method": "EdgeRegressor",
    "Retained": false,
    "SingularValue": 79.5354450834,
    "VarianceExplained": 0.0018396693
  },
  "dropped_11": {
    "CumulativeVarianceExplained": 0.541149485,
    "Mask": "Edge",
    "Method": "EdgeRegressor",
    "Retained": false,
    "SingularValue": 112.6616935472,
    "VarianceExplained": 0.0036912282
  },
  "dropped_110": {
    "CumulativeVarianceExplained": 0.7779175808,
    "Mask": "Edge",
    "Method": "EdgeRegressor",
    "Retained": false,
    "SingularValue": 79.3849911574,
    "VarianceExplained": 0.0018327159
  },
  "dropped_111": {
    "CumulativeVarianceExplained": 0.7797441287,
    "Mask": "Edge",
    "Method": "EdgeRegressor",
    "Retained": false,
    "SingularValue": 79.2512928618,
    "VarianceExplained": 0.0018265478
  },
  "dropped_112": {
    "CumulativeVarianceExplained": 0.7815641037,
    "Mask": "Edge",
    "Method": "EdgeRegressor",
    "Retained": false,
    "SingularValue": 79.1085726319,
    "VarianceExplained": 0.0018199751
  },
  "dropped_113": {
    "CumulativeVarianceExplained": 0.7833789087,
    "Mask": "Edge",
    "Method": "EdgeRegressor",
    "Retained": false,
    "SingularValue": 78.9961278957,
    "VarianceExplained": 0.0018148049
  },
  "dropped_114": {
    "CumulativeVarianceExplained": 0.7851876445,
    "Mask": "Edge",
    "Method": "EdgeRegressor",
    "Retained": false,
    "SingularValue": 78.8639273393,
    "VarianceExplained": 0.0018087358
  },
  "dropped_115": {
    "CumulativeVarianceExplained": 0.7869905622,
    "Mask": "Edge",
    "Method": "EdgeRegressor",
    "Retained": false,
    "SingularValue": 78.7369859007,
    "VarianceExplained": 0.0018029177
  },
  "dropped_116": {
    "CumulativeVarianceExplained": 0.7887868583,
    "Mask": "Edge",
    "Method": "EdgeRegressor",
    "Retained": false,
    "SingularValue": 78.5922623928,
    "VarianceExplained": 0.0017962961
  },
  "dropped_117": {
    "CumulativeVarianceExplained": 0.7905796067,
    "Mask": "Edge",
    "Method": "EdgeRegressor",
    "Retained": false,
    "SingularValue": 78.5146131987,
    "VarianceExplained": 0.0017927484
  },
  "dropped_118": {
    "CumulativeVarianceExplained": 0.7923673546,
    "Mask": "Edge",
    "Method": "EdgeRegressor",
    "Retained": false,
    "SingularValue": 78.4050374464,
    "VarianceExplained": 0.0017877479
  },
  "dropped_119": {
    "CumulativeVarianceExplained": 0.7941474055,
    "Mask": "Edge",
    "Method": "EdgeRegressor",
    "Retained": false,
    "SingularValue": 78.2360737287,
    "VarianceExplained": 0.001780051
  },
  "dropped_12": {
    "CumulativeVarianceExplained": 0.5447908608,
    "Mask": "Edge",
    "Method": "EdgeRegressor",
    "Retained": false,
    "SingularValue": 111.8983233239,
    "VarianceExplained": 0.0036413758
  },
  "dropped_120": {
    "CumulativeVarianceExplained": 0.7959257874,
    "Mask": "Edge",
    "Method": "EdgeRegressor",
    "Retained": false,
    "SingularValue": 78.19938607,
    "VarianceExplained": 0.0017783819
  },
  "dropped_121": {
    "CumulativeVarianceExplained": 0.7976991643,
    "Mask": "Edge",
    "Method": "EdgeRegressor",
    "Retained": false,
    "SingularValue": 78.0892686647,
    "VarianceExplained": 0.0017733769
  },
  "dropped_122": {
    "CumulativeVarianceExplained": 0.7994654357,
    "Mask": "Edge",
    "Method": "EdgeRegressor",
    "Retained": false,
    "SingularValue": 77.9326681615,
    "VarianceExplained": 0.0017662714
  },
  "dropped_123": {
    "CumulativeVarianceExplained": 0.8012258177,
    "Mask": "Edge",
    "Method": "EdgeRegressor",
    "Retained": false,
    "SingularValue": 77.8026325973,
    "VarianceExplained": 0.001760382
  },
  "dropped_124": {
    "CumulativeVarianceExplained": 0.8029759743,
    "Mask": "Edge",
    "Method": "EdgeRegressor",
    "Retained": false,
    "SingularValue": 77.5763388741,
    "VarianceExplained": 0.0017501566
  },
  "dropped_125": {
    "CumulativeVarianceExplained": 0.8047212119,
    "Mask": "Edge",
    "Method": "EdgeRegressor",
    "Retained": false,
    "SingularValue": 77.4672456704,
    "VarianceExplained": 0.0017452376
  },
  "dropped_126": {
    "CumulativeVarianceExplained": 0.8064593887,
    "Mask": "Edge",
    "Method": "EdgeRegressor",
    "Retained": false,
    "SingularValue": 77.3103794615,
    "VarianceExplained": 0.0017381768
  },
  "dropped_127": {
    "CumulativeVarianceExplained": 0.8081882077,
    "Mask": "Edge",
    "Method": "EdgeRegressor",
    "Retained": false,
    "SingularValue": 77.1019891581,
    "VarianceExplained": 0.0017288189
  },
  "dropped_128": {
    "CumulativeVarianceExplained": 0.8099154165,
    "Mask": "Edge",
    "Method": "EdgeRegressor",
    "Retained": false,
    "SingularValue": 77.066078498,
    "VarianceExplained": 0.0017272089
  },
  "dropped_129": {
    "CumulativeVarianceExplained": 0.8116372819,
    "Mask": "Edge",
    "Method": "EdgeRegressor",
    "Retained": false,
    "SingularValue": 76.9467758787,
    "VarianceExplained": 0.0017218654
  },
  "dropped_13": {
    "CumulativeVarianceExplained": 0.5483546886,
    "Mask": "Edge",
    "Method": "EdgeRegressor",
    "Retained": false,
    "SingularValue": 110.7003986569,
    "VarianceExplained": 0.0035638278
  },
  "dropped_130": {
    "CumulativeVarianceExplained": 0.8133528135,
    "Mask": "Edge",
    "Method": "EdgeRegressor",
    "Retained": false,
    "SingularValue": 76.8051221243,
    "VarianceExplained": 0.0017155315
  },
  "dropped_131": {
    "CumulativeVarianceExplained": 0.8150622346,
    "Mask": "Edge",
    "Method": "EdgeRegressor",
    "Retained": false,
    "SingularValue": 76.668216281,
    "VarianceExplained": 0.0017094211
  },
  "dropped_132": {
    "CumulativeVarianceExplained": 0.8167674572,
    "Mask": "Edge",
    "Method": "EdgeRegressor",
    "Retained": false,
    "SingularValue": 76.574005694,
    "VarianceExplained": 0.0017052226
  },
  "dropped_133": {
    "CumulativeVarianceExplained": 0.8184644267,
    "Mask": "Edge",
    "Method": "EdgeRegressor",
    "Retained": false,
    "SingularValue": 76.3884781735,
    "VarianceExplained": 0.0016969696
  },
  "dropped_134": {
    "CumulativeVarianceExplained": 0.8201576763,
    "Mask": "Edge",
    "Method": "EdgeRegressor",
    "Retained": false,
    "SingularValue": 76.3047051158,
    "VarianceExplained": 0.0016932496
  },
  "dropped_135": {
    "CumulativeVarianceExplained": 0.8218433565,
    "Mask": "Edge",
    "Method": "EdgeRegressor",
    "Retained": false,
    "SingularValue": 76.1339610251,
    "VarianceExplained": 0.0016856802
  },
  "dropped_136": {
    "CumulativeVarianceExplained": 0.8235253772,
    "Mask": "Edge",
    "Method": "EdgeRegressor",
    "Retained": false,
    "SingularValue": 76.0512734381,
    "VarianceExplained": 0.0016820206
  },
  "dropped_137": {
    "CumulativeVarianceExplained": 0.8251989856,
    "Mask": "Edge",
    "Method": "EdgeRegressor",
    "Retained": false,
    "SingularValue": 75.8608590757,
    "VarianceExplained": 0.0016736084
  },
  "dropped_138": {
    "CumulativeVarianceExplained": 0.8268682002,
    "Mask": "Edge",
    "Method": "EdgeRegressor",
    "Retained": false,
    "SingularValue": 75.7612131985,
    "VarianceExplained": 0.0016692146
  },
  "dropped_139": {
    "CumulativeVarianceExplained": 0.8285298254,
    "Mask": "Edge",
    "Method": "EdgeRegressor",
    "Retained": false,
    "SingularValue": 75.5887837679,
    "VarianceExplained": 0.0016616251
  },
  "dropped_14": {
    "CumulativeVarianceExplained": 0.5518318279,
    "Mask": "Edge",
    "Method": "EdgeRegressor",
    "Retained": false,
    "SingularValue": 109.3457421529,
    "VarianceExplained": 0.0034771393
  },
  "dropped_140": {
    "CumulativeVarianceExplained": 0.8301855338,
    "Mask": "Edge",
    "Method": "EdgeRegressor",
    "Retained": false,
    "SingularValue": 75.4540852679,
    "VarianceExplained": 0.0016557084
  },
  "dropped_141": {
    "CumulativeVarianceExplained": 0.8318339514,
    "Mask": "Edge",
    "Method": "EdgeRegressor",
    "Retained": false,
    "SingularValue": 75.2877727345,
    "VarianceExplained": 0.0016484176
  },
  "dropped_142": {
    "CumulativeVarianceExplained": 0.8334810452,
    "Mask": "Edge",
    "Method": "EdgeRegressor",
    "Retained": false,
    "SingularValue": 75.2575353978,
    "VarianceExplained": 0.0016470938
  },
  "dropped_143": {
    "CumulativeVarianceExplained": 0.8351210985,
    "Mask": "Edge",
    "Method": "EdgeRegressor",
    "Retained": false,
    "SingularValue": 75.0965213088,
    "VarianceExplained": 0.0016400534
  },
  "dropped_144": {
    "CumulativeVarianceExplained": 0.8367595059,
    "Mask": "Edge",
    "Method": "EdgeRegressor",
    "Retained": false,
    "SingularValue": 75.0588274563,
    "VarianceExplained": 0.0016384074
  },
  "dropped_145": {
    "CumulativeVarianceExplained": 0.8383929676,
    "Mask": "Edge",
    "Method": "EdgeRegressor",
    "Retained": false,
    "SingularValue": 74.9454564687,
    "VarianceExplained": 0.0016334617
  },
  "dropped_146": {
    "CumulativeVarianceExplained": 0.8400217143,
    "Mask": "Edge",
    "Method": "EdgeRegressor",
    "Retained": false,
    "SingularValue": 74.8372123524,
    "VarianceExplained": 0.0016287467
  },
  "dropped_147": {
    "CumulativeVarianceExplained": 0.8416421657,
    "Mask": "Edge",
    "Method": "EdgeRegressor",
    "Retained": false,
    "SingularValue": 74.6463940354,
    "VarianceExplained": 0.0016204514
  },
  "dropped_148": {
    "CumulativeVarianceExplained": 0.8432547594,
    "Mask": "Edge",
    "Method": "EdgeRegressor",
    "Retained": false,
    "SingularValue": 74.4651923078,
    "VarianceExplained": 0.0016125937
  },
  "dropped_149": {
    "CumulativeVarianceExplained": 0.8448640493,
    "Mask": "Edge",
    "Method": "EdgeRegressor",
    "Retained": false,
    "SingularValue": 74.3888716447,
    "VarianceExplained": 0.0016092899
  },
  "dropped_15": {
    "CumulativeVarianceExplained": 0.5552489339,
    "Mask": "Edge",
    "Method": "EdgeRegressor",
    "Retained": false,
    "SingularValue": 108.3976961447,
    "VarianceExplained": 0.003417106
  },
  "dropped_150": {
    "CumulativeVarianceExplained": 0.8464706327,
    "Mask": "Edge",
    "Method": "EdgeRegressor",
    "Retained": false,
    "SingularValue": 74.3262921059,
    "VarianceExplained": 0.0016065834
  },
  "dropped_151": {
    "CumulativeVarianceExplained": 0.8480709374,
    "Mask": "Edge",
    "Method": "EdgeRegressor",
    "Retained": false,
    "SingularValue": 74.1809122749,
    "VarianceExplained": 0.0016003047
  },
  "dropped_152": {
    "CumulativeVarianceExplained": 0.849668265,
    "Mask": "Edge",
    "Method": "EdgeRegressor",
    "Retained": false,
    "SingularValue": 74.1118775564,
    "VarianceExplained": 0.0015973275
  },
  "dropped_153": {
    "CumulativeVarianceExplained": 0.8512596098,
    "Mask": "Edge",
    "Method": "EdgeRegressor",
    "Retained": false,
    "SingularValue": 73.97295588,
    "VarianceExplained": 0.0015913448
  },
  "dropped_154": {
    "CumulativeVarianceExplained": 0.8528475439,
    "Mask": "Edge",
    "Method": "EdgeRegressor",
    "Retained": false,
    "SingularValue": 73.893641857,
    "VarianceExplained": 0.0015879341
  },
  "dropped_155": {
    "CumulativeVarianceExplained": 0.8544351873,
    "Mask": "Edge",
    "Method": "EdgeRegressor",
    "Retained": false,
    "SingularValue": 73.886878226,
    "VarianceExplained": 0.0015876435
  },
  "dropped_156": {
    "CumulativeVarianceExplained": 0.8560152284,
    "Mask": "Edge",
    "Method": "EdgeRegressor",
    "Retained": false,
    "SingularValue": 73.7097641879,
    "VarianceExplained": 0.0015800411
  },
  "dropped_157": {
    "CumulativeVarianceExplained": 0.8575864153,
    "Mask": "Edge",
    "Method": "EdgeRegressor",
    "Retained": false,
    "SingularValue": 73.5029467212,
    "VarianceExplained": 0.0015711869
  },
  "dropped_158": {
    "CumulativeVarianceExplained": 0.8591534237,
    "Mask": "Edge",
    "Method": "EdgeRegressor",
    "Retained": false,
    "SingularValue": 73.4051440956,
    "VarianceExplained": 0.0015670084
  },
  "dropped_159": {
    "CumulativeVarianceExplained": 0.8607161426,
    "Mask": "Edge",
    "Method": "EdgeRegressor",
    "Retained": false,
    "SingularValue": 73.304604144,
    "VarianceExplained": 0.0015627188
  },
  "dropped_16": {
    "CumulativeVarianceExplained": 0.5586363195,
    "Mask": "Edge",
    "Method": "EdgeRegressor",
    "Retained": false,
    "SingularValue": 107.9252711852,
    "VarianceExplained": 0.0033873856
  },
  "dropped_160": {
    "CumulativeVarianceExplained": 0.8622736612,
    "Mask": "Edge",
    "Method": "EdgeRegressor",
    "Retained": false,
    "SingularValue": 73.1825345502,
    "VarianceExplained": 0.0015575186
  },
  "dropped_161": {
    "CumulativeVarianceExplained": 0.8638258217,
    "Mask": "Edge",
    "Method": "EdgeRegressor",
    "Retained": false,
    "SingularValue": 73.0565472445,
    "VarianceExplained": 0.0015521605
  },
  "dropped_162": {
    "CumulativeVarianceExplained": 0.8653705459,
    "Mask": "Edge",
    "Method": "EdgeRegressor",
    "Retained": false,
    "SingularValue": 72.8813331978,
    "VarianceExplained": 0.0015447242
  },
  "dropped_163": {
    "CumulativeVarianceExplained": 0.8669111817,
    "Mask": "Edge",
    "Method": "EdgeRegressor",
    "Retained": false,
    "SingularValue": 72.7848225881,
    "VarianceExplained": 0.0015406358
  },
  "dropped_164": {
    "CumulativeVarianceExplained": 0.8684476448,
    "Mask": "Edge",
    "Method": "EdgeRegressor",
    "Retained": false,
    "SingularValue": 72.6861883803,
    "VarianceExplained": 0.0015364631
  },
  "dropped_165": {
    "CumulativeVarianceExplained": 0.8699791419,
    "Mask": "Edge",
    "Method": "EdgeRegressor",
    "Retained": false,
    "SingularValue": 72.5686285639,
    "VarianceExplained": 0.0015314971
  },
  "dropped_166": {
    "CumulativeVarianceExplained": 0.8715071876,
    "Mask": "Edge",
    "Method": "EdgeRegressor",
    "Retained": false,
    "SingularValue": 72.4868122994,
    "VarianceExplained": 0.0015280457
  },
  "dropped_167": {
    "CumulativeVarianceExplained": 0.8730321907,
    "Mask": "Edge",
    "Method": "EdgeRegressor",
    "Retained": false,
    "SingularValue": 72.4146098594,
    "VarianceExplained": 0.0015250031
  },
  "dropped_168": {
    "CumulativeVarianceExplained": 0.8745520906,
    "Mask": "Edge",
    "Method": "EdgeRegressor",
    "Retained": false,
    "SingularValue": 72.2933443101,
    "VarianceExplained": 0.0015198999
  },
  "dropped_169": {
    "CumulativeVarianceExplained": 0.8760644606,
    "Mask": "Edge",
    "Method": "EdgeRegressor",
    "Retained": false,
    "SingularValue": 72.1140457211,
    "VarianceExplained": 0.00151237
  },
  "dropped_17": {
    "CumulativeVarianceExplained": 0.5619578173,
    "Mask": "Edge",
    "Method": "EdgeRegressor",
    "Retained": false,
    "SingularValue": 106.8704930981,
    "VarianceExplained": 0.0033214978
  },
  "dropped_170": {
    "CumulativeVarianceExplained": 0.8775731305,
    "Mask": "Edge",
    "Method": "EdgeRegressor",
    "Retained": false,
    "SingularValue": 72.0257753857,
    "VarianceExplained": 0.0015086699
  },
  "dropped_171": {
    "CumulativeVarianceExplained": 0.8790728585,
    "Mask": "Edge",
    "Method": "EdgeRegressor",
    "Retained": false,
    "SingularValue": 71.8120091995,
    "VarianceExplained": 0.001499728
  },
  "dropped_172": {
    "CumulativeVarianceExplained": 0.8805686759,
    "Mask": "Edge",
    "Method": "EdgeRegressor",
    "Retained": false,
    "SingularValue": 71.7183223674,
    "VarianceExplained": 0.0014958174
  },
  "dropped_173": {
    "CumulativeVarianceExplained": 0.8820610424,
    "Mask": "Edge",
    "Method": "EdgeRegressor",
    "Retained": false,
    "SingularValue": 71.6355461647,
    "VarianceExplained": 0.0014923665
  },
  "dropped_174": {
    "CumulativeVarianceExplained": 0.8835486746,
    "Mask": "Edge",
    "Method": "EdgeRegressor",
    "Retained": false,
    "SingularValue": 71.5218304211,
    "VarianceExplained": 0.0014876322
  },
  "dropped_175": {
    "CumulativeVarianceExplained": 0.8850342897,
    "Mask": "Edge",
    "Method": "EdgeRegressor",
    "Retained": false,
    "SingularValue": 71.4733226854,
    "VarianceExplained": 0.001485615
  },
  "dropped_176": {
    "CumulativeVarianceExplained": 0.886512551,
    "Mask": "Edge",
    "Method": "EdgeRegressor",
    "Retained": false,
    "SingularValue": 71.2962088236,
    "VarianceExplained": 0.0014782613
  },
  "dropped_177": {
    "CumulativeVarianceExplained": 0.8879857696,
    "Mask": "Edge",
    "Method": "EdgeRegressor",
    "Retained": false,
    "SingularValue": 71.1745011083,
    "VarianceExplained": 0.0014732186
  },
  "dropped_178": {
    "CumulativeVarianceExplained": 0.8894548076,
    "Mask": "Edge",
    "Method": "EdgeRegressor",
    "Retained": false,
    "SingularValue": 71.0734405887,
    "VarianceExplained": 0.001469038
  },
  "dropped_179": {
    "CumulativeVarianceExplained": 0.8909205515,
    "Mask": "Edge",
    "Method": "EdgeRegressor",
    "Retained": false,
    "SingularValue": 70.9937108528,
    "VarianceExplained": 0.0014657439
  },
  "dropped_18": {
    "CumulativeVarianceExplained": 0.565265413,
    "Mask": "Edge",
    "Method": "EdgeRegressor",
    "Retained": false,
    "SingularValue": 106.6466058201,
    "VarianceExplained": 0.0033075957
  },
  "dropped_180": {
    "CumulativeVarianceExplained": 0.8923824979,
    "Mask": "Edge",
    "Method": "EdgeRegressor",
    "Retained": false,
    "SingularValue": 70.9016835002,
    "VarianceExplained": 0.0014619464
  },
  "dropped_181": {
    "CumulativeVarianceExplained": 0.8938399478,
    "Mask": "Edge",
    "Method": "EdgeRegressor",
    "Retained": false,
    "SingularValue": 70.792566189,
    "VarianceExplained": 0.00145745
  },
  "dropped_182": {
    "CumulativeVarianceExplained": 0.8952862413,
    "Mask": "Edge",
    "Method": "EdgeRegressor",
    "Retained": false,
    "SingularValue": 70.5210939059,
    "VarianceExplained": 0.0014462935
  },
  "dropped_183": {
    "CumulativeVarianceExplained": 0.8967313567,
    "Mask": "Edge",
    "Method": "EdgeRegressor",
    "Retained": false,
    "SingularValue": 70.4923668985,
    "VarianceExplained": 0.0014451154
  },
  "dropped_184": {
    "CumulativeVarianceExplained": 0.898168318,
    "Mask": "Edge",
    "Method": "EdgeRegressor",
    "Retained": false,
    "SingularValue": 70.2932089376,
    "VarianceExplained": 0.0014369613
  },
  "dropped_185": {
    "CumulativeVarianceExplained": 0.8996037444,
    "Mask": "Edge",
    "Method": "EdgeRegressor",
    "Retained": false,
    "SingularValue": 70.2556559585,
    "VarianceExplained": 0.0014354264
  },
  "dropped_186": {
    "CumulativeVarianceExplained": 0.9010372912,
    "Mask": "Edge",
    "Method": "EdgeRegressor",
    "Retained": false,
    "SingularValue": 70.2096432351,
    "VarianceExplained": 0.0014335468
  },
  "dropped_187": {
    "CumulativeVarianceExplained": 0.9024664948,
    "Mask": "Edge",
    "Method": "EdgeRegressor",
    "Retained": false,
    "SingularValue": 70.1032072069,
    "VarianceExplained": 0.0014292036
  },
  "dropped_188": {
    "CumulativeVarianceExplained": 0.9038897104,
    "Mask": "Edge",
    "Method": "EdgeRegressor",
    "Retained": false,
    "SingularValue": 69.956193826,
    "VarianceExplained": 0.0014232156
  },
  "dropped_189": {
    "CumulativeVarianceExplained": 0.905306486,
    "Mask": "Edge",
    "Method": "EdgeRegressor",
    "Retained": false,
    "SingularValue": 69.7977392881,
    "VarianceExplained": 0.0014167756
  },
  "dropped_19": {
    "CumulativeVarianceExplained": 0.5684832103,
    "Mask": "Edge",
    "Method": "EdgeRegressor",
    "Retained": false,
    "SingularValue": 105.188962247,
    "VarianceExplained": 0.0032177973
  },
  "dropped_190": {
    "CumulativeVarianceExplained": 0.90671691,
    "Mask": "Edge",
    "Method": "EdgeRegressor",
    "Retained": false,
    "SingularValue": 69.6411090158,
    "VarianceExplained": 0.001410424
  },
  "dropped_191": {
    "CumulativeVarianceExplained": 0.9081259019,
    "Mask": "Edge",
    "Method": "EdgeRegressor",
    "Retained": false,
    "SingularValue": 69.6057430425,
    "VarianceExplained": 0.0014089919
  },
  "dropped_192": {
    "CumulativeVarianceExplained": 0.9095290966,
    "Mask": "Edge",
    "Method": "EdgeRegressor",
    "Retained": false,
    "SingularValue": 69.4624034266,
    "VarianceExplained": 0.0014031948
  },
  "dropped_193": {
    "CumulativeVarianceExplained": 0.9109262671,
    "Mask": "Edge",
    "Method": "EdgeRegressor",
    "Retained": false,
    "SingularValue": 69.3131325633,
    "VarianceExplained": 0.0013971705
  },
  "dropped_194": {
    "CumulativeVarianceExplained": 0.9123191116,
    "Mask": "Edge",
    "Method": "EdgeRegressor",
    "Retained": false,
    "SingularValue": 69.2057448661,
    "VarianceExplained": 0.0013928445
  },
  "dropped_195": {
    "CumulativeVarianceExplained": 0.913704383,
    "Mask": "Edge",
    "Method": "EdgeRegressor",
    "Retained": false,
    "SingularValue": 69.017348065,
    "VarianceExplained": 0.0013852714
  },
  "dropped_196": {
    "CumulativeVarianceExplained": 0.9150859606,
    "Mask": "Edge",
    "Method": "EdgeRegressor",
    "Retained": false,
    "SingularValue": 68.9252697131,
    "VarianceExplained": 0.0013815776
  },
  "dropped_197": {
    "CumulativeVarianceExplained": 0.9164640726,
    "Mask": "Edge",
    "Method": "EdgeRegressor",
    "Retained": false,
    "SingularValue": 68.838765966,
    "VarianceExplained": 0.0013781119
  },
  "dropped_198": {
    "CumulativeVarianceExplained": 0.9178381906,
    "Mask": "Edge",
    "Method": "EdgeRegressor",
    "Retained": false,
    "SingularValue": 68.7389418678,
    "VarianceExplained": 0.001374118
  },
  "dropped_199": {
    "CumulativeVarianceExplained": 0.9192096733,
    "Mask": "Edge",
    "Method": "EdgeRegressor",
    "Retained": false,
    "SingularValue": 68.6729980145,
    "VarianceExplained": 0.0013714828
  },
  "dropped_2": {
    "CumulativeVarianceExplained": 0.5038173662,
    "Mask": "Edge",
    "Method": "EdgeRegressor",
    "Retained": false,
    "SingularValue": 130.2181624859,
    "VarianceExplained": 0.0049313005
  },
  "dropped_20": {
    "CumulativeVarianceExplained": 0.5716902908,
    "Mask": "Edge",
    "Method": "EdgeRegressor",
    "Retained": false,
    "SingularValue": 105.013651064,
    "VarianceExplained": 0.0032070805
  },
  "dropped_200": {
    "CumulativeVarianceExplained": 0.9205780969,
    "Mask": "Edge",
    "Method": "EdgeRegressor",
    "Retained": false,
    "SingularValue": 68.5963653557,
    "VarianceExplained": 0.0013684236
  },
  "dropped_201": {
    "CumulativeVarianceExplained": 0.9219405909,
    "Mask": "Edge",
    "Method": "EdgeRegressor",
    "Retained": false,
    "SingularValue": 68.4475836267,
    "VarianceExplained": 0.001362494
  },
  "dropped_202": {
    "CumulativeVarianceExplained": 0.9232999918,
    "Mask": "Edge",
    "Method": "EdgeRegressor",
    "Retained": false,
    "SingularValue": 68.3698467435,
    "VarianceExplained": 0.0013594009
  },
  "dropped_203": {
    "CumulativeVarianceExplained": 0.9246540601,
    "Mask": "Edge",
    "Method": "EdgeRegressor",
    "Retained": false,
    "SingularValue": 68.23561527,
    "VarianceExplained": 0.0013540683
  },
  "dropped_204": {
    "CumulativeVarianceExplained": 0.9260022524,
    "Mask": "Edge",
    "Method": "EdgeRegressor",
    "Retained": false,
    "SingularValue": 68.0874001355,
    "VarianceExplained": 0.0013481923
  },
  "dropped_205": {
    "CumulativeVarianceExplained": 0.9273488112,
    "Mask": "Edge",
    "Method": "EdgeRegressor",
    "Retained": false,
    "SingularValue": 68.0461397116,
    "VarianceExplained": 0.0013465588
  },
  "dropped_206": {
    "CumulativeVarianceExplained": 0.9286912347,
    "Mask": "Edge",
    "Method": "EdgeRegressor",
    "Retained": false,
    "SingularValue": 67.9415735288,
    "VarianceExplained": 0.0013424235
  },
  "dropped_207": {
    "CumulativeVarianceExplained": 0.9300239922,
    "Mask": "Edge",
    "Method": "EdgeRegressor",
    "Retained": false,
    "SingularValue": 67.696529257,
    "VarianceExplained": 0.0013327575
  },
  "dropped_208": {
    "CumulativeVarianceExplained": 0.9313540664,
    "Mask": "Edge",
    "Method": "EdgeRegressor",
    "Retained": false,
    "SingularValue": 67.6283462609,
    "VarianceExplained": 0.0013300742
  },
  "dropped_209": {
    "CumulativeVarianceExplained": 0.9326794158,
    "Mask": "Edge",
    "Method": "EdgeRegressor",
    "Retained": false,
    "SingularValue": 67.5081212631,
    "VarianceExplained": 0.0013253494
  },
  "dropped_21": {
    "CumulativeVarianceExplained": 0.5748257827,
    "Mask": "Edge",
    "Method": "EdgeRegressor",
    "Retained": false,
    "SingularValue": 103.8349783576,
    "VarianceExplained": 0.003135492
  },
  "dropped_210": {
    "CumulativeVarianceExplained": 0.9340038696,
    "Mask": "Edge",
    "Method": "EdgeRegressor",
    "Retained": false,
    "SingularValue": 67.4853073048,
    "VarianceExplained": 0.0013244538
  },
  "dropped_211": {
    "CumulativeVarianceExplained": 0.9353209873,
    "Mask": "Edge",
    "Method": "EdgeRegressor",
    "Retained": false,
    "SingularValue": 67.298151201,
    "VarianceExplained": 0.0013171178
  },
  "dropped_212": {
    "CumulativeVarianceExplained": 0.9366348422,
    "Mask": "Edge",
    "Method": "EdgeRegressor",
    "Retained": false,
    "SingularValue": 67.214740175,
    "VarianceExplained": 0.0013138549
  },
  "dropped_213": {
    "CumulativeVarianceExplained": 0.9379409357,
    "Mask": "Edge",
    "Method": "EdgeRegressor",
    "Retained": false,
    "SingularValue": 67.0159165641,
    "VarianceExplained": 0.0013060935
  },
  "dropped_214": {
    "CumulativeVarianceExplained": 0.9392441155,
    "Mask": "Edge",
    "Method": "EdgeRegressor",
    "Retained": false,
    "SingularValue": 66.9411251523,
    "VarianceExplained": 0.0013031799
  },
  "dropped_215": {
    "CumulativeVarianceExplained": 0.9405389261,
    "Mask": "Edge",
    "Method": "EdgeRegressor",
    "Retained": false,
    "SingularValue": 66.725823591,
    "VarianceExplained": 0.0012948105
  },
  "dropped_216": {
    "CumulativeVarianceExplained": 0.9418281248,
    "Mask": "Edge",
    "Method": "EdgeRegressor",
    "Retained": false,
    "SingularValue": 66.5810684954,
    "VarianceExplained": 0.0012891987
  },
  "dropped_217": {
    "CumulativeVarianceExplained": 0.943116535,
    "Mask": "Edge",
    "Method": "EdgeRegressor",
    "Retained": false,
    "SingularValue": 66.5607051516,
    "VarianceExplained": 0.0012884102
  },
  "dropped_218": {
    "CumulativeVarianceExplained": 0.9443981794,
    "Mask": "Edge",
    "Method": "EdgeRegressor",
    "Retained": false,
    "SingularValue": 66.3857093395,
    "VarianceExplained": 0.0012816444
  },
  "dropped_219": {
    "CumulativeVarianceExplained": 0.9456752842,
    "Mask": "Edge",
    "Method": "EdgeRegressor",
    "Retained": false,
    "SingularValue": 66.2680348598,
    "VarianceExplained": 0.0012771048
  },
  "dropped_22": {
    "CumulativeVarianceExplained": 0.5779283708,
    "Mask": "Edge",
    "Method": "EdgeRegressor",
    "Retained": false,
    "SingularValue": 103.2887180197,
    "VarianceExplained": 0.0031025881
  },
  "dropped_220": {
    "CumulativeVarianceExplained": 0.9469518515,
    "Mask": "Edge",
    "Method": "EdgeRegressor",
    "Retained": false,
    "SingularValue": 66.2540901107,
    "VarianceExplained": 0.0012765673
  },
  "dropped_221": {
    "CumulativeVarianceExplained": 0.9482235474,
    "Mask": "Edge",
    "Method": "EdgeRegressor",
    "Retained": false,
    "SingularValue": 66.1275532168,
    "VarianceExplained": 0.0012716958
  },
  "dropped_222": {
    "CumulativeVarianceExplained": 0.9494897065,
    "Mask": "Edge",
    "Method": "EdgeRegressor",
    "Retained": false,
    "SingularValue": 65.9834423196,
    "VarianceExplained": 0.0012661591
  },
  "dropped_223": {
    "CumulativeVarianceExplained": 0.9507530424,
    "Mask": "Edge",
    "Method": "EdgeRegressor",
    "Retained": false,
    "SingularValue": 65.9098404713,
    "VarianceExplained": 0.001263336
  },
  "dropped_224": {
    "CumulativeVarianceExplained": 0.9520137299,
    "Mask": "Edge",
    "Method": "EdgeRegressor",
    "Retained": false,
    "SingularValue": 65.8407151507,
    "VarianceExplained": 0.0012606874
  },
  "dropped_225": {
    "CumulativeVarianceExplained": 0.9532636135,
    "Mask": "Edge",
    "Method": "EdgeRegressor",
    "Retained": false,
    "SingularValue": 65.5579892711,
    "VarianceExplained": 0.0012498837
  },
  "dropped_226": {
    "CumulativeVarianceExplained": 0.9545105043,
    "Mask": "Edge",
    "Method": "EdgeRegressor",
    "Retained": false,
    "SingularValue": 65.4794529512,
    "VarianceExplained": 0.0012468908
  },
  "dropped_227": {
    "CumulativeVarianceExplained": 0.9557532629,
    "Mask": "Edge",
    "Method": "EdgeRegressor",
    "Retained": false,
    "SingularValue": 65.3708627279,
    "VarianceExplained": 0.0012427586
  },
  "dropped_228": {
    "CumulativeVarianceExplained": 0.9569897641,
    "Mask": "Edge",
    "Method": "EdgeRegressor",
    "Retained": false,
    "SingularValue": 65.2060805103,
    "VarianceExplained": 0.0012365012
  },
  "dropped_229": {
    "CumulativeVarianceExplained": 0.9582211709,
    "Mask": "Edge",
    "Method": "EdgeRegressor",
    "Retained": false,
    "SingularValue": 65.0716166366,
    "VarianceExplained": 0.0012314068
  },
  "dropped_23": {
    "CumulativeVarianceExplained": 0.5809856545,
    "Mask": "Edge",
    "Method": "EdgeRegressor",
    "Retained": false,
    "SingularValue": 102.5318283206,
    "VarianceExplained": 0.0030572837
  },
  "dropped_230": {
    "CumulativeVarianceExplained": 0.959448177,
    "Mask": "Edge",
    "Method": "EdgeRegressor",
    "Retained": false,
    "SingularValue": 64.9552403996,
    "VarianceExplained": 0.0012270061
  },
  "dropped_231": {
    "CumulativeVarianceExplained": 0.9606715659,
    "Mask": "Edge",
    "Method": "EdgeRegressor",
    "Retained": false,
    "SingularValue": 64.8594247225,
    "VarianceExplained": 0.0012233889
  },
  "dropped_232": {
    "CumulativeVarianceExplained": 0.961893012,
    "Mask": "Edge",
    "Method": "EdgeRegressor",
    "Retained": false,
    "SingularValue": 64.8079066755,
    "VarianceExplained": 0.0012214462
  },
  "dropped_233": {
    "CumulativeVarianceExplained": 0.9631048128,
    "Mask": "Edge",
    "Method": "EdgeRegressor",
    "Retained": false,
    "SingularValue": 64.5515152191,
    "VarianceExplained": 0.0012118008
  },
  "dropped_234": {
    "CumulativeVarianceExplained": 0.9643132663,
    "Mask": "Edge",
    "Method": "EdgeRegressor",
    "Retained": false,
    "SingularValue": 64.4623013759,
    "VarianceExplained": 0.0012084535
  },
  "dropped_235": {
    "CumulativeVarianceExplained": 0.9655180023,
    "Mask": "Edge",
    "Method": "EdgeRegressor",
    "Retained": false,
    "SingularValue": 64.3630738097,
    "VarianceExplained": 0.001204736
  },
  "dropped_236": {
    "CumulativeVarianceExplained": 0.9667161066,
    "Mask": "Edge",
    "Method": "EdgeRegressor",
    "Retained": false,
    "SingularValue": 64.1856797333,
    "VarianceExplained": 0.0011981043
  },
  "dropped_237": {
    "CumulativeVarianceExplained": 0.9679125108,
    "Mask": "Edge",
    "Method": "EdgeRegressor",
    "Retained": false,
    "SingularValue": 64.1401231956,
    "VarianceExplained": 0.0011964042
  },
  "dropped_238": {
    "CumulativeVarianceExplained": 0.9691003901,
    "Mask": "Edge",
    "Method": "EdgeRegressor",
    "Retained": false,
    "SingularValue": 63.9112029391,
    "VarianceExplained": 0.0011878793
  },
  "dropped_239": {
    "CumulativeVarianceExplained": 0.9702867064,
    "Mask": "Edge",
    "Method": "EdgeRegressor",
    "Retained": false,
    "SingularValue": 63.8691399169,
    "VarianceExplained": 0.0011863162
  },
  "dropped_24": {
    "CumulativeVarianceExplained": 0.5840113659,
    "Mask": "Edge",
    "Method": "EdgeRegressor",
    "Retained": false,
    "SingularValue": 102.001035739,
    "VarianceExplained": 0.0030257114
  },
  "dropped_240": {
    "CumulativeVarianceExplained": 0.9714662682,
    "Mask": "Edge",
    "Method": "EdgeRegressor",
    "Retained": false,
    "SingularValue": 63.6870578278,
    "VarianceExplained": 0.0011795618
  },
  "dropped_241": {
    "CumulativeVarianceExplained": 0.9726432864,
    "Mask": "Edge",
    "Method": "EdgeRegressor",
    "Retained": false,
    "SingularValue": 63.6183520997,
    "VarianceExplained": 0.0011770182
  },
  "dropped_242": {
    "CumulativeVarianceExplained": 0.9738179674,
    "Mask": "Edge",
    "Method": "EdgeRegressor",
    "Retained": false,
    "SingularValue": 63.5551575501,
    "VarianceExplained": 0.001174681
  },
  "dropped_243": {
    "CumulativeVarianceExplained": 0.9749831726,
    "Mask": "Edge",
    "Method": "EdgeRegressor",
    "Retained": false,
    "SingularValue": 63.2982978943,
    "VarianceExplained": 0.0011652052
  },
  "dropped_244": {
    "CumulativeVarianceExplained": 0.9761409371,
    "Mask": "Edge",
    "Method": "EdgeRegressor",
    "Retained": false,
    "SingularValue": 63.095873144,
    "VarianceExplained": 0.0011577646
  },
  "dropped_245": {
    "CumulativeVarianceExplained": 0.9772942327,
    "Mask": "Edge",
    "Method": "EdgeRegressor",
    "Retained": false,
    "SingularValue": 62.9739794757,
    "VarianceExplained": 0.0011532956
  },
  "dropped_246": {
    "CumulativeVarianceExplained": 0.978442907,
    "Mask": "Edge",
    "Method": "EdgeRegressor",
    "Retained": false,
    "SingularValue": 62.8476853989,
    "VarianceExplained": 0.0011486743
  },
  "dropped_247": {
    "CumulativeVarianceExplained": 0.9795868425,
    "Mask": "Edge",
    "Method": "EdgeRegressor",
    "Retained": false,
    "SingularValue": 62.7179134843,
    "VarianceExplained": 0.0011439355
  },
  "dropped_248": {
    "CumulativeVarianceExplained": 0.9807293702,
    "Mask": "Edge",
    "Method": "EdgeRegressor",
    "Retained": false,
    "SingularValue": 62.6793088782,
    "VarianceExplained": 0.0011425277
  },
  "dropped_249": {
    "CumulativeVarianceExplained": 0.9818630227,
    "Mask": "Edge",
    "Method": "EdgeRegressor",
    "Retained": false,
    "SingularValue": 62.4353859116,
    "VarianceExplained": 0.0011336525
  },
  "dropped_25": {
    "CumulativeVarianceExplained": 0.5870173911,
    "Mask": "Edge",
    "Method": "EdgeRegressor",
    "Retained": false,
    "SingularValue": 101.6686681386,
    "VarianceExplained": 0.0030060252
  },
  "dropped_250": {
    "CumulativeVarianceExplained": 0.9829928673,
    "Mask": "Edge",
    "Method": "EdgeRegressor",
    "Retained": false,
    "SingularValue": 62.3304390929,
    "VarianceExplained": 0.0011298446
  },
  "dropped_251": {
    "CumulativeVarianceExplained": 0.9841155543,
    "Mask": "Edge",
    "Method": "EdgeRegressor",
    "Retained": false,
    "SingularValue": 62.1326927723,
    "VarianceExplained": 0.001122687
  },
  "dropped_252": {
    "CumulativeVarianceExplained": 0.9852282289,
    "Mask": "Edge",
    "Method": "EdgeRegressor",
    "Retained": false,
    "SingularValue": 61.855014383,
    "VarianceExplained": 0.0011126746
  },
  "dropped_253": {
    "CumulativeVarianceExplained": 0.9863391655,
    "Mask": "Edge",
    "Method": "EdgeRegressor",
    "Retained": false,
    "SingularValue": 61.8066869043,
    "VarianceExplained": 0.0011109366
  },
  "dropped_254": {
    "CumulativeVarianceExplained": 0.9874480931,
    "Mask": "Edge",
    "Method": "EdgeRegressor",
    "Retained": false,
    "SingularValue": 61.7507774491,
    "VarianceExplained": 0.0011089276
  },
  "dropped_255": {
    "CumulativeVarianceExplained": 0.9885535131,
    "Mask": "Edge",
    "Method": "EdgeRegressor",
    "Retained": false,
    "SingularValue": 61.6530397627,
    "VarianceExplained": 0.00110542
  },
  "dropped_256": {
    "CumulativeVarianceExplained": 0.9896541372,
    "Mask": "Edge",
    "Method": "EdgeRegressor",
    "Retained": false,
    "SingularValue": 61.5191502321,
    "VarianceExplained": 0.001100624
  },
  "dropped_257": {
    "CumulativeVarianceExplained": 0.9907438408,
    "Mask": "Edge",
    "Method": "EdgeRegressor",
    "Retained": false,
    "SingularValue": 61.2131922384,
    "VarianceExplained": 0.0010897036
  },
  "dropped_258": {
    "CumulativeVarianceExplained": 0.991822229,
    "Mask": "Edge",
    "Method": "EdgeRegressor",
    "Retained": false,
    "SingularValue": 60.8945466305,
    "VarianceExplained": 0.0010783882
  },
  "dropped_259": {
    "CumulativeVarianceExplained": 0.9928919024,
    "Mask": "Edge",
    "Method": "EdgeRegressor",
    "Retained": false,
    "SingularValue": 60.64799026,
    "VarianceExplained": 0.0010696733
  },
  "dropped_26": {
    "CumulativeVarianceExplained": 0.5899816743,
    "Mask": "Edge",
    "Method": "EdgeRegressor",
    "Retained": false,
    "SingularValue": 100.9603097674,
    "VarianceExplained": 0.0029642832
  },
  "dropped_260": {
    "CumulativeVarianceExplained": 0.9939547043,
    "Mask": "Edge",
    "Method": "EdgeRegressor",
    "Retained": false,
    "SingularValue": 60.4528806279,
    "VarianceExplained": 0.0010628019
  },
  "dropped_261": {
    "CumulativeVarianceExplained": 0.995011927,
    "Mask": "Edge",
    "Method": "EdgeRegressor",
    "Retained": false,
    "SingularValue": 60.2939967599,
    "VarianceExplained": 0.0010572227
  },
  "dropped_262": {
    "CumulativeVarianceExplained": 0.996062033,
    "Mask": "Edge",
    "Method": "EdgeRegressor",
    "Retained": false,
    "SingularValue": 60.0907183234,
    "VarianceExplained": 0.001050106
  },
  "dropped_263": {
    "CumulativeVarianceExplained": 0.9971029245,
    "Mask": "Edge",
    "Method": "EdgeRegressor",
    "Retained": false,
    "SingularValue": 59.8264942692,
    "VarianceExplained": 0.0010408915
  },
  "dropped_264": {
    "CumulativeVarianceExplained": 0.9981305578,
    "Mask": "Edge",
    "Method": "EdgeRegressor",
    "Retained": false,
    "SingularValue": 59.4442594123,
    "VarianceExplained": 0.0010276333
  },
  "dropped_265": {
    "CumulativeVarianceExplained": 0.9991556048,
    "Mask": "Edge",
    "Method": "EdgeRegressor",
    "Retained": false,
    "SingularValue": 59.3694062616,
    "VarianceExplained": 0.0010250469
  },
  "dropped_266": {
    "CumulativeVarianceExplained": 1.0,
    "Mask": "Edge",
    "Method": "EdgeRegressor",
    "Retained": false,
    "SingularValue": 53.8844823539,
    "VarianceExplained": 0.0008443952
  },
  "dropped_267": {
    "CumulativeVarianceExplained": 1.0,
    "Mask": "Edge",
    "Method": "EdgeRegressor",
    "Retained": false,
    "SingularValue": 0.0,
    "VarianceExplained": 0.0
  },
  "dropped_268": {
    "CumulativeVarianceExplained": 1.0,
    "Mask": "Edge",
    "Method": "EdgeRegressor",
    "Retained": false,
    "SingularValue": 0.0,
    "VarianceExplained": 0.0
  },
  "dropped_269": {
    "CumulativeVarianceExplained": 1.0,
    "Mask": "Edge",
    "Method": "EdgeRegressor",
    "Retained": false,
    "SingularValue": 0.0,
    "VarianceExplained": 0.0
  },
  "dropped_27": {
    "CumulativeVarianceExplained": 0.592901009,
    "Mask": "Edge",
    "Method": "EdgeRegressor",
    "Retained": false,
    "SingularValue": 100.1919371443,
    "VarianceExplained": 0.0029193347
  },
  "dropped_270": {
    "CumulativeVarianceExplained": 1.0,
    "Mask": "Edge",
    "Method": "EdgeRegressor",
    "Retained": false,
    "SingularValue": 0.0,
    "VarianceExplained": 0.0
  },
  "dropped_271": {
    "CumulativeVarianceExplained": 1.0,
    "Mask": "Edge",
    "Method": "EdgeRegressor",
    "Retained": false,
    "SingularValue": 0.0,
    "VarianceExplained": 0.0
  },
  "dropped_272": {
    "CumulativeVarianceExplained": 1.0,
    "Mask": "Edge",
    "Method": "EdgeRegressor",
    "Retained": false,
    "SingularValue": 0.0,
    "VarianceExplained": 0.0
  },
  "dropped_273": {
    "CumulativeVarianceExplained": 1.0,
    "Mask": "Edge",
    "Method": "EdgeRegressor",
    "Retained": false,
    "SingularValue": 0.0,
    "VarianceExplained": 0.0
  },
  "dropped_274": {
    "CumulativeVarianceExplained": 1.0,
    "Mask": "Edge",
    "Method": "EdgeRegressor",
    "Retained": false,
    "SingularValue": 0.0,
    "VarianceExplained": 0.0
  },
  "dropped_275": {
    "CumulativeVarianceExplained": 1.0,
    "Mask": "Edge",
    "Method": "EdgeRegressor",
    "Retained": false,
    "SingularValue": 0.0,
    "VarianceExplained": 0.0
  },
  "dropped_28": {
    "CumulativeVarianceExplained": 0.595800726,
    "Mask": "Edge",
    "Method": "EdgeRegressor",
    "Retained": false,
    "SingularValue": 99.8547296548,
    "VarianceExplained": 0.002899717
  },
  "dropped_29": {
    "CumulativeVarianceExplained": 0.5986767201,
    "Mask": "Edge",
    "Method": "EdgeRegressor",
    "Retained": false,
    "SingularValue": 99.4454292027,
    "VarianceExplained": 0.0028759941
  },
  "dropped_3": {
    "CumulativeVarianceExplained": 0.508593221,
    "Mask": "Edge",
    "Method": "EdgeRegressor",
    "Retained": false,
    "SingularValue": 128.1493442473,
    "VarianceExplained": 0.0047758548
  },
  "dropped_30": {
    "CumulativeVarianceExplained": 0.601524225,
    "Mask": "Edge",
    "Method": "EdgeRegressor",
    "Retained": false,
    "SingularValue": 98.9516568103,
    "VarianceExplained": 0.0028475049
  },
  "dropped_31": {
    "CumulativeVarianceExplained": 0.6043623834,
    "Mask": "Edge",
    "Method": "EdgeRegressor",
    "Retained": false,
    "SingularValue": 98.78912594,
    "VarianceExplained": 0.0028381584
  },
  "dropped_32": {
    "CumulativeVarianceExplained": 0.6071599062,
    "Mask": "Edge",
    "Method": "EdgeRegressor",
    "Retained": false,
    "SingularValue": 98.0793657991,
    "VarianceExplained": 0.0027975228
  },
  "dropped_33": {
    "CumulativeVarianceExplained": 0.6099409574,
    "Mask": "Edge",
    "Method": "EdgeRegressor",
    "Retained": false,
    "SingularValue": 97.7901966737,
    "VarianceExplained": 0.0027810512
  },
  "dropped_34": {
    "CumulativeVarianceExplained": 0.6126956679,
    "Mask": "Edge",
    "Method": "EdgeRegressor",
    "Retained": false,
    "SingularValue": 97.325985378,
    "VarianceExplained": 0.0027547105
  },
  "dropped_35": {
    "CumulativeVarianceExplained": 0.615394256,
    "Mask": "Edge",
    "Method": "EdgeRegressor",
    "Retained": false,
    "SingularValue": 96.3294618226,
    "VarianceExplained": 0.0026985882
  },
  "dropped_36": {
    "CumulativeVarianceExplained": 0.6180751297,
    "Mask": "Edge",
    "Method": "EdgeRegressor",
    "Retained": false,
    "SingularValue": 96.0127714555,
    "VarianceExplained": 0.0026808737
  },
  "dropped_37": {
    "CumulativeVarianceExplained": 0.6207479077,
    "Mask": "Edge",
    "Method": "EdgeRegressor",
    "Retained": false,
    "SingularValue": 95.8676908298,
    "VarianceExplained": 0.0026727779
  },
  "dropped_38": {
    "CumulativeVarianceExplained": 0.6233693067,
    "Mask": "Edge",
    "Method": "EdgeRegressor",
    "Retained": false,
    "SingularValue": 94.9417863463,
    "VarianceExplained": 0.0026213991
  },
  "dropped_39": {
    "CumulativeVarianceExplained": 0.625973966,
    "Mask": "Edge",
    "Method": "EdgeRegressor",
    "Retained": false,
    "SingularValue": 94.6381609908,
    "VarianceExplained": 0.0026046593
  },
  "dropped_4": {
    "CumulativeVarianceExplained": 0.5131393893,
    "Mask": "Edge",
    "Method": "EdgeRegressor",
    "Retained": false,
    "SingularValue": 125.0298141498,
    "VarianceExplained": 0.0045461683
  },
  "dropped_40": {
    "CumulativeVarianceExplained": 0.6285549082,
    "Mask": "Edge",
    "Method": "EdgeRegressor",
    "Retained": false,
    "SingularValue": 94.2063035838,
    "VarianceExplained": 0.0025809421
  },
  "dropped_41": {
    "CumulativeVarianceExplained": 0.6311154907,
    "Mask": "Edge",
    "Method": "EdgeRegressor",
    "Retained": false,
    "SingularValue": 93.8339982401,
    "VarianceExplained": 0.0025605826
  },
  "dropped_42": {
    "CumulativeVarianceExplained": 0.6336463766,
    "Mask": "Edge",
    "Method": "EdgeRegressor",
    "Retained": false,
    "SingularValue": 93.2882850137,
    "VarianceExplained": 0.0025308859
  },
  "dropped_43": {
    "CumulativeVarianceExplained": 0.6361731266,
    "Mask": "Edge",
    "Method": "EdgeRegressor",
    "Retained": false,
    "SingularValue": 93.2120307064,
    "VarianceExplained": 0.00252675
  },
  "dropped_44": {
    "CumulativeVarianceExplained": 0.6386653986,
    "Mask": "Edge",
    "Method": "EdgeRegressor",
    "Retained": false,
    "SingularValue": 92.5738978466,
    "VarianceExplained": 0.002492272
  },
  "dropped_45": {
    "CumulativeVarianceExplained": 0.6411366315,
    "Mask": "Edge",
    "Method": "EdgeRegressor",
    "Retained": false,
    "SingularValue": 92.1823266791,
    "VarianceExplained": 0.0024712329
  },
  "dropped_46": {
    "CumulativeVarianceExplained": 0.6436029925,
    "Mask": "Edge",
    "Method": "EdgeRegressor",
    "Retained": false,
    "SingularValue": 92.0914158846,
    "VarianceExplained": 0.002466361
  },
  "dropped_47": {
    "CumulativeVarianceExplained": 0.6460477116,
    "Mask": "Edge",
    "Method": "EdgeRegressor",
    "Retained": false,
    "SingularValue": 91.6864831646,
    "VarianceExplained": 0.0024447191
  },
  "dropped_48": {
    "CumulativeVarianceExplained": 0.6484802269,
    "Mask": "Edge",
    "Method": "EdgeRegressor",
    "Retained": false,
    "SingularValue": 91.4573508191,
    "VarianceExplained": 0.0024325153
  },
  "dropped_49": {
    "CumulativeVarianceExplained": 0.6508943801,
    "Mask": "Edge",
    "Method": "EdgeRegressor",
    "Retained": false,
    "SingularValue": 91.111508777,
    "VarianceExplained": 0.0024141532
  },
  "dropped_5": {
    "CumulativeVarianceExplained": 0.5175005165,
    "Mask": "Edge",
    "Method": "EdgeRegressor",
    "Retained": false,
    "SingularValue": 122.4588571754,
    "VarianceExplained": 0.0043611271
  },
  "dropped_50": {
    "CumulativeVarianceExplained": 0.6533004043,
    "Mask": "Edge",
    "Method": "EdgeRegressor",
    "Retained": false,
    "SingularValue": 90.9579851102,
    "VarianceExplained": 0.0024060243
  },
  "dropped_51": {
    "CumulativeVarianceExplained": 0.6556916781,
    "Mask": "Edge",
    "Method": "EdgeRegressor",
    "Retained": false,
    "SingularValue": 90.6787404821,
    "VarianceExplained": 0.0023912738
  },
  "dropped_52": {
    "CumulativeVarianceExplained": 0.6580779869,
    "Mask": "Edge",
    "Method": "EdgeRegressor",
    "Retained": false,
    "SingularValue": 90.5845551049,
    "VarianceExplained": 0.0023863089
  },
  "dropped_53": {
    "CumulativeVarianceExplained": 0.6604399917,
    "Mask": "Edge",
    "Method": "EdgeRegressor",
    "Retained": false,
    "SingularValue": 90.1220807657,
    "VarianceExplained": 0.0023620047
  },
  "dropped_54": {
    "CumulativeVarianceExplained": 0.662787659,
    "Mask": "Edge",
    "Method": "EdgeRegressor",
    "Retained": false,
    "SingularValue": 89.8481440902,
    "VarianceExplained": 0.0023476674
  },
  "dropped_55": {
    "CumulativeVarianceExplained": 0.6651139163,
    "Mask": "Edge",
    "Method": "EdgeRegressor",
    "Retained": false,
    "SingularValue": 89.4375103864,
    "VarianceExplained": 0.0023262573
  },
  "dropped_56": {
    "CumulativeVarianceExplained": 0.6674268769,
    "Mask": "Edge",
    "Method": "EdgeRegressor",
    "Retained": false,
    "SingularValue": 89.1815356099,
    "VarianceExplained": 0.0023129606
  },
  "dropped_57": {
    "CumulativeVarianceExplained": 0.6697201935,
    "Mask": "Edge",
    "Method": "EdgeRegressor",
    "Retained": false,
    "SingularValue": 88.8020180899,
    "VarianceExplained": 0.0022933166
  },
  "dropped_58": {
    "CumulativeVarianceExplained": 0.6720078557,
    "Mask": "Edge",
    "Method": "EdgeRegressor",
    "Retained": false,
    "SingularValue": 88.6924767604,
    "VarianceExplained": 0.0022876623
  },
  "dropped_59": {
    "CumulativeVarianceExplained": 0.6742891334,
    "Mask": "Edge",
    "Method": "EdgeRegressor",
    "Retained": false,
    "SingularValue": 88.5686241992,
    "VarianceExplained": 0.0022812776
  },
  "dropped_6": {
    "CumulativeVarianceExplained": 0.5217113466,
    "Mask": "Edge",
    "Method": "EdgeRegressor",
    "Retained": false,
    "SingularValue": 120.330214675,
    "VarianceExplained": 0.0042108302
  },
  "dropped_60": {
    "CumulativeVarianceExplained": 0.6765637803,
    "Mask": "Edge",
    "Method": "EdgeRegressor",
    "Retained": false,
    "SingularValue": 88.4398158084,
    "VarianceExplained": 0.002274647
  },
  "dropped_61": {
    "CumulativeVarianceExplained": 0.6788295932,
    "Mask": "Edge",
    "Method": "EdgeRegressor",
    "Retained": false,
    "SingularValue": 88.2679121512,
    "VarianceExplained": 0.0022658129
  },
  "dropped_62": {
    "CumulativeVarianceExplained": 0.6810878825,
    "Mask": "Edge",
    "Method": "EdgeRegressor",
    "Retained": false,
    "SingularValue": 88.1212430859,
    "VarianceExplained": 0.0022582893
  },
  "dropped_63": {
    "CumulativeVarianceExplained": 0.6833400634,
    "Mask": "Edge",
    "Method": "EdgeRegressor",
    "Retained": false,
    "SingularValue": 88.0019844153,
    "VarianceExplained": 0.0022521809
  },
  "dropped_64": {
    "CumulativeVarianceExplained": 0.6855818795,
    "Mask": "Edge",
    "Method": "EdgeRegressor",
    "Retained": false,
    "SingularValue": 87.7992524852,
    "VarianceExplained": 0.0022418161
  },
  "dropped_65": {
    "CumulativeVarianceExplained": 0.6878049423,
    "Mask": "Edge",
    "Method": "EdgeRegressor",
    "Retained": false,
    "SingularValue": 87.4312512778,
    "VarianceExplained": 0.0022230628
  },
  "dropped_66": {
    "CumulativeVarianceExplained": 0.6900138409,
    "Mask": "Edge",
    "Method": "EdgeRegressor",
    "Retained": false,
    "SingularValue": 87.1522738965,
    "VarianceExplained": 0.0022088986
  },
  "dropped_67": {
    "CumulativeVarianceExplained": 0.692214519,
    "Mask": "Edge",
    "Method": "EdgeRegressor",
    "Retained": false,
    "SingularValue": 86.9899514306,
    "VarianceExplained": 0.0022006781
  },
  "dropped_68": {
    "CumulativeVarianceExplained": 0.6943970546,
    "Mask": "Edge",
    "Method": "EdgeRegressor",
    "Retained": false,
    "SingularValue": 86.630634615,
    "VarianceExplained": 0.0021825356
  },
  "dropped_69": {
    "CumulativeVarianceExplained": 0.6965740229,
    "Mask": "Edge",
    "Method": "EdgeRegressor",
    "Retained": false,
    "SingularValue": 86.5200739603,
    "VarianceExplained": 0.0021769683
  },
  "dropped_7": {
    "CumulativeVarianceExplained": 0.5257619043,
    "Mask": "Edge",
    "Method": "EdgeRegressor",
    "Retained": false,
    "SingularValue": 118.017997175,
    "VarianceExplained": 0.0040505577
  },
  "dropped_70": {
    "CumulativeVarianceExplained": 0.6987432414,
    "Mask": "Edge",
    "Method": "EdgeRegressor",
    "Retained": false,
    "SingularValue": 86.3659350025,
    "VarianceExplained": 0.0021692185
  },
  "dropped_71": {
    "CumulativeVarianceExplained": 0.7008987289,
    "Mask": "Edge",
    "Method": "EdgeRegressor",
    "Retained": false,
    "SingularValue": 86.0921566019,
    "VarianceExplained": 0.0021554875
  },
  "dropped_72": {
    "CumulativeVarianceExplained": 0.7030424629,
    "Mask": "Edge",
    "Method": "EdgeRegressor",
    "Retained": false,
    "SingularValue": 85.8571130351,
    "VarianceExplained": 0.002143734
  },
  "dropped_73": {
    "CumulativeVarianceExplained": 0.7051824622,
    "Mask": "Edge",
    "Method": "EdgeRegressor",
    "Retained": false,
    "SingularValue": 85.7822907065,
    "VarianceExplained": 0.0021399992
  },
  "dropped_74": {
    "CumulativeVarianceExplained": 0.707299436,
    "Mask": "Edge",
    "Method": "EdgeRegressor",
    "Retained": false,
    "SingularValue": 85.3195542585,
    "VarianceExplained": 0.0021169739
  },
  "dropped_75": {
    "CumulativeVarianceExplained": 0.7094107527,
    "Mask": "Edge",
    "Method": "EdgeRegressor",
    "Retained": false,
    "SingularValue": 85.205477034,
    "VarianceExplained": 0.0021113166
  },
  "dropped_76": {
    "CumulativeVarianceExplained": 0.7115211645,
    "Mask": "Edge",
    "Method": "EdgeRegressor",
    "Retained": false,
    "SingularValue": 85.1872183566,
    "VarianceExplained": 0.0021104118
  },
  "dropped_77": {
    "CumulativeVarianceExplained": 0.7136141057,
    "Mask": "Edge",
    "Method": "EdgeRegressor",
    "Retained": false,
    "SingularValue": 84.8338818568,
    "VarianceExplained": 0.0020929412
  },
  "dropped_78": {
    "CumulativeVarianceExplained": 0.7156976966,
    "Mask": "Edge",
    "Method": "EdgeRegressor",
    "Retained": false,
    "SingularValue": 84.6441712791,
    "VarianceExplained": 0.0020835909
  },
  "dropped_79": {
    "CumulativeVarianceExplained": 0.7177711499,
    "Mask": "Edge",
    "Method": "EdgeRegressor",
    "Retained": false,
    "SingularValue": 84.4380041983,
    "VarianceExplained": 0.0020734533
  },
  "dropped_8": {
    "CumulativeVarianceExplained": 0.529791604,
    "Mask": "Edge",
    "Method": "EdgeRegressor",
    "Retained": false,
    "SingularValue": 117.7137432145,
    "VarianceExplained": 0.0040296997
  },
  "dropped_80": {
    "CumulativeVarianceExplained": 0.7198315071,
    "Mask": "Edge",
    "Method": "EdgeRegressor",
    "Retained": false,
    "SingularValue": 84.1709232982,
    "VarianceExplained": 0.0020603572
  },
  "dropped_81": {
    "CumulativeVarianceExplained": 0.7218878088,
    "Mask": "Edge",
    "Method": "EdgeRegressor",
    "Retained": false,
    "SingularValue": 84.0880432032,
    "VarianceExplained": 0.0020563017
  },
  "dropped_82": {
    "CumulativeVarianceExplained": 0.7239375449,
    "Mask": "Edge",
    "Method": "EdgeRegressor",
    "Retained": false,
    "SingularValue": 83.953692977,
    "VarianceExplained": 0.0020497361
  },
  "dropped_83": {
    "CumulativeVarianceExplained": 0.7259720016,
    "Mask": "Edge",
    "Method": "EdgeRegressor",
    "Retained": false,
    "SingularValue": 83.6401972322,
    "VarianceExplained": 0.0020344566
  },
  "dropped_84": {
    "CumulativeVarianceExplained": 0.7279969862,
    "Mask": "Edge",
    "Method": "EdgeRegressor",
    "Retained": false,
    "SingularValue": 83.4452641638,
    "VarianceExplained": 0.0020249846
  },
  "dropped_85": {
    "CumulativeVarianceExplained": 0.7300091662,
    "Mask": "Edge",
    "Method": "EdgeRegressor",
    "Retained": false,
    "SingularValue": 83.1810201317,
    "VarianceExplained": 0.00201218
  },
  "dropped_86": {
    "CumulativeVarianceExplained": 0.732012952,
    "Mask": "Edge",
    "Method": "EdgeRegressor",
    "Retained": false,
    "SingularValue": 83.0073368696,
    "VarianceExplained": 0.0020037858
  },
  "dropped_87": {
    "CumulativeVarianceExplained": 0.7340102765,
    "Mask": "Edge",
    "Method": "EdgeRegressor",
    "Retained": false,
    "SingularValue": 82.8733981368,
    "VarianceExplained": 0.0019973245
  },
  "dropped_88": {
    "CumulativeVarianceExplained": 0.7359987247,
    "Mask": "Edge",
    "Method": "EdgeRegressor",
    "Retained": false,
    "SingularValue": 82.6890444102,
    "VarianceExplained": 0.0019884482
  },
  "dropped_89": {
    "CumulativeVarianceExplained": 0.7379837781,
    "Mask": "Edge",
    "Method": "EdgeRegressor",
    "Retained": false,
    "SingularValue": 82.6184275551,
    "VarianceExplained": 0.0019850534
  },
  "dropped_9": {
    "CumulativeVarianceExplained": 0.533677924,
    "Mask": "Edge",
    "Method": "EdgeRegressor",
    "Retained": false,
    "SingularValue": 115.6006057263,
    "VarianceExplained": 0.00388632
  },
  "dropped_90": {
    "CumulativeVarianceExplained": 0.7399577995,
    "Mask": "Edge",
    "Method": "EdgeRegressor",
    "Retained": false,
    "SingularValue": 82.3885301892,
    "VarianceExplained": 0.0019740214
  },
  "dropped_91": {
    "CumulativeVarianceExplained": 0.741920121,
    "Mask": "Edge",
    "Method": "EdgeRegressor",
    "Retained": false,
    "SingularValue": 82.1440112343,
    "VarianceExplained": 0.0019623215
  },
  "dropped_92": {
    "CumulativeVarianceExplained": 0.7438756117,
    "Mask": "Edge",
    "Method": "EdgeRegressor",
    "Retained": false,
    "SingularValue": 82.0009176359,
    "VarianceExplained": 0.0019554908
  },
  "dropped_93": {
    "CumulativeVarianceExplained": 0.745824659,
    "Mask": "Edge",
    "Method": "EdgeRegressor",
    "Retained": false,
    "SingularValue": 81.8657059262,
    "VarianceExplained": 0.0019490472
  },
  "dropped_94": {
    "CumulativeVarianceExplained": 0.7477705216,
    "Mask": "Edge",
    "Method": "EdgeRegressor",
    "Retained": false,
    "SingularValue": 81.7987984481,
    "VarianceExplained": 0.0019458627
  },
  "dropped_95": {
    "CumulativeVarianceExplained": 0.7497065053,
    "Mask": "Edge",
    "Method": "EdgeRegressor",
    "Retained": false,
    "SingularValue": 81.5908915079,
    "VarianceExplained": 0.0019359837
  },
  "dropped_96": {
    "CumulativeVarianceExplained": 0.7516351914,
    "Mask": "Edge",
    "Method": "EdgeRegressor",
    "Retained": false,
    "SingularValue": 81.4369692211,
    "VarianceExplained": 0.0019286861
  },
  "dropped_97": {
    "CumulativeVarianceExplained": 0.7535588815,
    "Mask": "Edge",
    "Method": "EdgeRegressor",
    "Retained": false,
    "SingularValue": 81.3314259956,
    "VarianceExplained": 0.0019236901
  },
  "dropped_98": {
    "CumulativeVarianceExplained": 0.7554689015,
    "Mask": "Edge",
    "Method": "EdgeRegressor",
    "Retained": false,
    "SingularValue": 81.0419313515,
    "VarianceExplained": 0.00191002
  },
  "dropped_99": {
    "CumulativeVarianceExplained": 0.7573767773,
    "Mask": "Edge",
    "Method": "EdgeRegressor",
    "Retained": false,
    "SingularValue": 80.9964292351,
    "VarianceExplained": 0.0019078757
  },
  "edge_comp_00": {
    "CumulativeVarianceExplained": 0.1035218993,
    "Mask": "Edge",
    "Method": "EdgeRegressor",
    "Retained": true,
    "SingularValue": 596.6325526635,
    "VarianceExplained": 0.1035218993
  },
  "edge_comp_01": {
    "CumulativeVarianceExplained": 0.1691532187,
    "Mask": "Edge",
    "Method": "EdgeRegressor",
    "Retained": true,
    "SingularValue": 475.0577384003,
    "VarianceExplained": 0.0656313194
  },
  "edge_comp_02": {
    "CumulativeVarianceExplained": 0.2310971162,
    "Mask": "Edge",
    "Method": "EdgeRegressor",
    "Retained": true,
    "SingularValue": 461.519540415,
    "VarianceExplained": 0.0619438976
  },
  "edge_comp_03": {
    "CumulativeVarianceExplained": 0.2763225082,
    "Mask": "Edge",
    "Method": "EdgeRegressor",
    "Retained": true,
    "SingularValue": 394.3501397514,
    "VarianceExplained": 0.0452253919
  },
  "edge_comp_04": {
    "CumulativeVarianceExplained": 0.3004975279,
    "Mask": "Edge",
    "Method": "EdgeRegressor",
    "Retained": true,
    "SingularValue": 288.319653778,
    "VarianceExplained": 0.0241750197
  },
  "edge_comp_05": {
    "CumulativeVarianceExplained": 0.3188918044,
    "Mask": "Edge",
    "Method": "EdgeRegressor",
    "Retained": true,
    "SingularValue": 251.4966387666,
    "VarianceExplained": 0.0183942765
  },
  "edge_comp_06": {
    "CumulativeVarianceExplained": 0.335770651,
    "Mask": "Edge",
    "Method": "EdgeRegressor",
    "Retained": true,
    "SingularValue": 240.9140965975,
    "VarianceExplained": 0.0168788466
  },
  "edge_comp_07": {
    "CumulativeVarianceExplained": 0.3513830854,
    "Mask": "Edge",
    "Method": "EdgeRegressor",
    "Retained": true,
    "SingularValue": 231.7000575974,
    "VarianceExplained": 0.0156124343
  },
  "edge_comp_08": {
    "CumulativeVarianceExplained": 0.3663411821,
    "Mask": "Edge",
    "Method": "EdgeRegressor",
    "Retained": true,
    "SingularValue": 226.7926621284,
    "VarianceExplained": 0.0149580968
  },
  "edge_comp_09": {
    "CumulativeVarianceExplained": 0.3797836742,
    "Mask": "Edge",
    "Method": "EdgeRegressor",
    "Retained": true,
    "SingularValue": 214.9961699013,
    "VarianceExplained": 0.013442492
  },
  "edge_comp_10": {
    "CumulativeVarianceExplained": 0.3920667849,
    "Mask": "Edge",
    "Method": "EdgeRegressor",
    "Retained": true,
    "SingularValue": 205.5157040279,
    "VarianceExplained": 0.0122831107
  },
  "edge_comp_11": {
    "CumulativeVarianceExplained": 0.4030172881,
    "Mask": "Edge",
    "Method": "EdgeRegressor",
    "Retained": true,
    "SingularValue": 194.0474174559,
    "VarianceExplained": 0.0109505032
  },
  "edge_comp_12": {
    "CumulativeVarianceExplained": 0.4129894022,
    "Mask": "Edge",
    "Method": "EdgeRegressor",
    "Retained": true,
    "SingularValue": 185.1758937853,
    "VarianceExplained": 0.0099721141
  },
  "edge_comp_13": {
    "CumulativeVarianceExplained": 0.4221302698,
    "Mask": "Edge",
    "Method": "EdgeRegressor",
    "Retained": true,
    "SingularValue": 177.2901221157,
    "VarianceExplained": 0.0091408676
  },
  "edge_comp_14": {
    "CumulativeVarianceExplained": 0.4308756987,
    "Mask": "Edge",
    "Method": "EdgeRegressor",
    "Retained": true,
    "SingularValue": 173.4128939212,
    "VarianceExplained": 0.0087454289
  },
  "edge_comp_15": {
    "CumulativeVarianceExplained": 0.4385382834,
    "Mask": "Edge",
    "Method": "EdgeRegressor",
    "Retained": true,
    "SingularValue": 162.3224062698,
    "VarianceExplained": 0.0076625846
  },
  "edge_comp_16": {
    "CumulativeVarianceExplained": 0.4458730499,
    "Mask": "Edge",
    "Method": "EdgeRegressor",
    "Retained": true,
    "SingularValue": 158.8122420184,
    "VarianceExplained": 0.0073347665
  },
  "edge_comp_17": {
    "CumulativeVarianceExplained": 0.452839114,
    "Mask": "Edge",
    "Method": "EdgeRegressor",
    "Retained": true,
    "SingularValue": 154.7692093286,
    "VarianceExplained": 0.0069660641
  },
  "edge_comp_18": {
    "CumulativeVarianceExplained": 0.459642583,
    "Mask": "Edge",
    "Method": "EdgeRegressor",
    "Retained": true,
    "SingularValue": 152.9523076512,
    "VarianceExplained": 0.006803469
  },
  "edge_comp_19": {
    "CumulativeVarianceExplained": 0.4658546038,
    "Mask": "Edge",
    "Method": "EdgeRegressor",
    "Retained": true,
    "SingularValue": 146.1528473534,
    "VarianceExplained": 0.0062120208
  },
  "edge_comp_20": {
    "CumulativeVarianceExplained": 0.4717254231,
    "Mask": "Edge",
    "Method": "EdgeRegressor",
    "Retained": true,
    "SingularValue": 142.0823670889,
    "VarianceExplained": 0.0058708192
  },
  "edge_comp_21": {
    "CumulativeVarianceExplained": 0.4774653585,
    "Mask": "Edge",
    "Method": "EdgeRegressor",
    "Retained": true,
    "SingularValue": 140.4896504867,
    "VarianceExplained": 0.0057399354
  },
  "edge_comp_22": {
    "CumulativeVarianceExplained": 0.4831014331,
    "Mask": "Edge",
    "Method": "EdgeRegressor",
    "Retained": true,
    "SingularValue": 139.2128087188,
    "VarianceExplained": 0.0056360746
  },
  "edge_comp_23": {
    "CumulativeVarianceExplained": 0.4885881569,
    "Mask": "Edge",
    "Method": "EdgeRegressor",
    "Retained": true,
    "SingularValue": 137.3559196642,
    "VarianceExplained": 0.0054867239
  },
  "t_comp_cor_00": {
    "CumulativeVarianceExplained": 0.1219035737,
    "Method": "tCompCor",
    "Retained": true,
    "SingularValue": 168.7864484231,
    "VarianceExplained": 0.1219035737
  },
  "t_comp_cor_01": {
    "CumulativeVarianceExplained": 0.2325607242,
    "Method": "tCompCor",
    "Retained": true,
    "SingularValue": 160.8122386033,
    "VarianceExplained": 0.1106571506
  },
  "t_comp_cor_02": {
    "CumulativeVarianceExplained": 0.3154020343,
    "Method": "tCompCor",
    "Retained": true,
    "SingularValue": 139.1402679519,
    "VarianceExplained": 0.0828413101
  },
  "t_comp_cor_03": {
    "CumulativeVarianceExplained": 0.373256945,
    "Method": "tCompCor",
    "Retained": true,
    "SingularValue": 116.2785132007,
    "VarianceExplained": 0.0578549107
  },
  "t_comp_cor_04": {
    "CumulativeVarianceExplained": 0.4270366124,
    "Method": "tCompCor",
    "Retained": true,
    "SingularValue": 112.1084665451,
    "VarianceExplained": 0.0537796674
  },
  "t_comp_cor_05": {
    "CumulativeVarianceExplained": 0.4743742633,
    "Method": "tCompCor",
    "Retained": true,
    "SingularValue": 105.1798888006,
    "VarianceExplained": 0.0473376509
  },
  "t_comp_cor_06": {
    "CumulativeVarianceExplained": 0.5202013138,
    "Method": "tCompCor",
    "Retained": true,
    "SingularValue": 103.4880751545,
    "VarianceExplained": 0.0458270505
  },
  "w_comp_cor_00": {
    "CumulativeVarianceExplained": 0.0346646773,
    "Mask": "WM",
    "Method": "aCompCor",
    "Retained": true,
    "SingularValue": 138.0655860847,
    "VarianceExplained": 0.0346646773
  },
  "w_comp_cor_01": {
    "CumulativeVarianceExplained": 0.0585890249,
    "Mask": "WM",
    "Method": "aCompCor",
    "Retained": true,
    "SingularValue": 114.6996022,
    "VarianceExplained": 0.0239243476
  },
  "w_comp_cor_02": {
    "CumulativeVarianceExplained": 0.0780687765,
    "Mask": "WM",
    "Method": "aCompCor",
    "Retained": true,
    "SingularValue": 103.4983835591,
    "VarianceExplained": 0.0194797516
  },
  "w_comp_cor_03": {
    "CumulativeVarianceExplained": 0.0934100014,
    "Mask": "WM",
    "Method": "aCompCor",
    "Retained": true,
    "SingularValue": 91.8484597446,
    "VarianceExplained": 0.0153412249
  },
  "w_comp_cor_04": {
    "CumulativeVarianceExplained": 0.1067208723,
    "Mask": "WM",
    "Method": "aCompCor",
    "Retained": true,
    "SingularValue": 85.5549407739,
    "VarianceExplained": 0.0133108709
  },
  "w_comp_cor_05": {
    "CumulativeVarianceExplained": 0.1190427687,
    "Mask": "WM",
    "Method": "aCompCor",
    "Retained": true,
    "SingularValue": 82.3153137455,
    "VarianceExplained": 0.0123218965
  },
  "w_comp_cor_06": {
    "CumulativeVarianceExplained": 0.1301409371,
    "Mask": "WM",
    "Method": "aCompCor",
    "Retained": true,
    "SingularValue": 78.1209496479,
    "VarianceExplained": 0.0110981683
  },
  "w_comp_cor_07": {
    "CumulativeVarianceExplained": 0.140984264,
    "Mask": "WM",
    "Method": "aCompCor",
    "Retained": true,
    "SingularValue": 77.2188156129,
    "VarianceExplained": 0.0108433269
  },
  "w_comp_cor_08": {
    "CumulativeVarianceExplained": 0.1513124739,
    "Mask": "WM",
    "Method": "aCompCor",
    "Retained": true,
    "SingularValue": 75.3623421135,
    "VarianceExplained": 0.0103282099
  },
  "w_comp_cor_09": {
    "CumulativeVarianceExplained": 0.1614808186,
    "Mask": "WM",
    "Method": "aCompCor",
    "Retained": true,
    "SingularValue": 74.7768194475,
    "VarianceExplained": 0.0101683447
  },
  "w_comp_cor_10": {
    "CumulativeVarianceExplained": 0.1712548047,
    "Mask": "WM",
    "Method": "aCompCor",
    "Retained": true,
    "SingularValue": 73.3124477757,
    "VarianceExplained": 0.0097739862
  },
  "w_comp_cor_11": {
    "CumulativeVarianceExplained": 0.1808430799,
    "Mask": "WM",
    "Method": "aCompCor",
    "Retained": true,
    "SingularValue": 72.6126195569,
    "VarianceExplained": 0.0095882752
  },
  "w_comp_cor_12": {
    "CumulativeVarianceExplained": 0.189723929,
    "Mask": "WM",
    "Method": "aCompCor",
    "Retained": true,
    "SingularValue": 69.8826080296,
    "VarianceExplained": 0.0088808491
  },
  "w_comp_cor_13": {
    "CumulativeVarianceExplained": 0.198361598,
    "Mask": "WM",
    "Method": "aCompCor",
    "Retained": true,
    "SingularValue": 68.91918598,
    "VarianceExplained": 0.008637669
  },
  "w_comp_cor_14": {
    "CumulativeVarianceExplained": 0.2066397308,
    "Mask": "WM",
    "Method": "aCompCor",
    "Retained": true,
    "SingularValue": 67.4695872184,
    "VarianceExplained": 0.0082781328
  },
  "w_comp_cor_15": {
    "CumulativeVarianceExplained": 0.2148165437,
    "Mask": "WM",
    "Method": "aCompCor",
    "Retained": true,
    "SingularValue": 67.0554205072,
    "VarianceExplained": 0.0081768129
  },
  "w_comp_cor_16": {
    "CumulativeVarianceExplained": 0.2228693906,
    "Mask": "WM",
    "Method": "aCompCor",
    "Retained": true,
    "SingularValue": 66.5451764663,
    "VarianceExplained": 0.0080528469
  },
  "w_comp_cor_17": {
    "CumulativeVarianceExplained": 0.2307816692,
    "Mask": "WM",
    "Method": "aCompCor",
    "Retained": true,
    "SingularValue": 65.961822339,
    "VarianceExplained": 0.0079122786
  },
  "w_comp_cor_18": {
    "CumulativeVarianceExplained": 0.2386192132,
    "Mask": "WM",
    "Method": "aCompCor",
    "Retained": true,
    "SingularValue": 65.649565646,
    "VarianceExplained": 0.007837544
  },
  "w_comp_cor_19": {
    "CumulativeVarianceExplained": 0.24625777,
    "Mask": "WM",
    "Method": "aCompCor",
    "Retained": true,
    "SingularValue": 64.8108197325,
    "VarianceExplained": 0.0076385567
  },
  "w_comp_cor_20": {
    "CumulativeVarianceExplained": 0.2535001094,
    "Mask": "WM",
    "Method": "aCompCor",
    "Retained": true,
    "SingularValue": 63.1075466121,
    "VarianceExplained": 0.0072423394
  },
  "w_comp_cor_21": {
    "CumulativeVarianceExplained": 0.2607116077,
    "Mask": "WM",
    "Method": "aCompCor",
    "Retained": true,
    "SingularValue": 62.9730334441,
    "VarianceExplained": 0.0072114983
  },
  "w_comp_cor_22": {
    "CumulativeVarianceExplained": 0.2676069891,
    "Mask": "WM",
    "Method": "aCompCor",
    "Retained": true,
    "SingularValue": 61.5773517335,
    "VarianceExplained": 0.0068953814
  },
  "w_comp_cor_23": {
    "CumulativeVarianceExplained": 0.2744662902,
    "Mask": "WM",
    "Method": "aCompCor",
    "Retained": true,
    "SingularValue": 61.4160374999,
    "VarianceExplained": 0.0068593011
  },
  "w_comp_cor_24": {
    "CumulativeVarianceExplained": 0.2812026699,
    "Mask": "WM",
    "Method": "aCompCor",
    "Retained": true,
    "SingularValue": 60.8632496547,
    "VarianceExplained": 0.0067363796
  },
  "w_comp_cor_25": {
    "CumulativeVarianceExplained": 0.2878285704,
    "Mask": "WM",
    "Method": "aCompCor",
    "Retained": true,
    "SingularValue": 60.3620967703,
    "VarianceExplained": 0.0066259006
  },
  "w_comp_cor_26": {
    "CumulativeVarianceExplained": 0.2942639324,
    "Mask": "WM",
    "Method": "aCompCor",
    "Retained": true,
    "SingularValue": 59.4878604653,
    "VarianceExplained": 0.006435362
  },
  "w_comp_cor_27": {
    "CumulativeVarianceExplained": 0.3006643017,
    "Mask": "WM",
    "Method": "aCompCor",
    "Retained": true,
    "SingularValue": 59.325905586,
    "VarianceExplained": 0.0064003693
  },
  "w_comp_cor_28": {
    "CumulativeVarianceExplained": 0.3070218456,
    "Mask": "WM",
    "Method": "aCompCor",
    "Retained": true,
    "SingularValue": 59.1270952199,
    "VarianceExplained": 0.0063575439
  },
  "w_comp_cor_29": {
    "CumulativeVarianceExplained": 0.3131787199,
    "Mask": "WM",
    "Method": "aCompCor",
    "Retained": true,
    "SingularValue": 58.186468896,
    "VarianceExplained": 0.0061568743
  },
  "w_comp_cor_30": {
    "CumulativeVarianceExplained": 0.3192751461,
    "Mask": "WM",
    "Method": "aCompCor",
    "Retained": true,
    "SingularValue": 57.9001277046,
    "VarianceExplained": 0.0060964262
  },
  "w_comp_cor_31": {
    "CumulativeVarianceExplained": 0.3253417965,
    "Mask": "WM",
    "Method": "aCompCor",
    "Retained": true,
    "SingularValue": 57.758558556,
    "VarianceExplained": 0.0060666505
  },
  "w_comp_cor_32": {
    "CumulativeVarianceExplained": 0.3313871609,
    "Mask": "WM",
    "Method": "aCompCor",
    "Retained": true,
    "SingularValue": 57.6571405775,
    "VarianceExplained": 0.0060453644
  },
  "w_comp_cor_33": {
    "CumulativeVarianceExplained": 0.3373060607,
    "Mask": "WM",
    "Method": "aCompCor",
    "Retained": true,
    "SingularValue": 57.0508808542,
    "VarianceExplained": 0.0059188998
  },
  "w_comp_cor_34": {
    "CumulativeVarianceExplained": 0.3431925935,
    "Mask": "WM",
    "Method": "aCompCor",
    "Retained": true,
    "SingularValue": 56.8946780211,
    "VarianceExplained": 0.0058865328
  },
  "w_comp_cor_35": {
    "CumulativeVarianceExplained": 0.3489703421,
    "Mask": "WM",
    "Method": "aCompCor",
    "Retained": true,
    "SingularValue": 56.3665142607,
    "VarianceExplained": 0.0057777486
  },
  "w_comp_cor_36": {
    "CumulativeVarianceExplained": 0.3547225903,
    "Mask": "WM",
    "Method": "aCompCor",
    "Retained": true,
    "SingularValue": 56.2419888901,
    "VarianceExplained": 0.0057522483
  },
  "w_comp_cor_37": {
    "CumulativeVarianceExplained": 0.3603545217,
    "Mask": "WM",
    "Method": "aCompCor",
    "Retained": true,
    "SingularValue": 55.6506879152,
    "VarianceExplained": 0.0056319314
  },
  "w_comp_cor_38": {
    "CumulativeVarianceExplained": 0.3659712576,
    "Mask": "WM",
    "Method": "aCompCor",
    "Retained": true,
    "SingularValue": 55.575561583,
    "VarianceExplained": 0.0056167359
  },
  "w_comp_cor_39": {
    "CumulativeVarianceExplained": 0.3715427437,
    "Mask": "WM",
    "Method": "aCompCor",
    "Retained": true,
    "SingularValue": 55.3512442102,
    "VarianceExplained": 0.0055714862
  },
  "w_comp_cor_40": {
    "CumulativeVarianceExplained": 0.3770646022,
    "Mask": "WM",
    "Method": "aCompCor",
    "Retained": true,
    "SingularValue": 55.1041737638,
    "VarianceExplained": 0.0055218585
  },
  "w_comp_cor_41": {
    "CumulativeVarianceExplained": 0.3825299399,
    "Mask": "WM",
    "Method": "aCompCor",
    "Retained": true,
    "SingularValue": 54.821430164,
    "VarianceExplained": 0.0054653377
  },
  "w_comp_cor_42": {
    "CumulativeVarianceExplained": 0.3879530437,
    "Mask": "WM",
    "Method": "aCompCor",
    "Retained": true,
    "SingularValue": 54.6092006876,
    "VarianceExplained": 0.0054231038
  },
  "w_comp_cor_43": {
    "CumulativeVarianceExplained": 0.3933257734,
    "Mask": "WM",
    "Method": "aCompCor",
    "Retained": true,
    "SingularValue": 54.3549818023,
    "VarianceExplained": 0.0053727297
  },
  "w_comp_cor_44": {
    "CumulativeVarianceExplained": 0.398628185,
    "Mask": "WM",
    "Method": "aCompCor",
    "Retained": true,
    "SingularValue": 53.9981126512,
    "VarianceExplained": 0.0053024117
  },
  "w_comp_cor_45": {
    "CumulativeVarianceExplained": 0.403904596,
    "Mask": "WM",
    "Method": "aCompCor",
    "Retained": true,
    "SingularValue": 53.8655586852,
    "VarianceExplained": 0.005276411
  },
  "w_comp_cor_46": {
    "CumulativeVarianceExplained": 0.4091016574,
    "Mask": "WM",
    "Method": "aCompCor",
    "Retained": true,
    "SingularValue": 53.4589939297,
    "VarianceExplained": 0.0051970613
  },
  "w_comp_cor_47": {
    "CumulativeVarianceExplained": 0.4142777343,
    "Mask": "WM",
    "Method": "aCompCor",
    "Retained": true,
    "SingularValue": 53.3509579432,
    "VarianceExplained": 0.0051760769
  },
  "w_comp_cor_48": {
    "CumulativeVarianceExplained": 0.4194166515,
    "Mask": "WM",
    "Method": "aCompCor",
    "Retained": true,
    "SingularValue": 53.1591058854,
    "VarianceExplained": 0.0051389171
  },
  "w_comp_cor_49": {
    "CumulativeVarianceExplained": 0.4245199271,
    "Mask": "WM",
    "Method": "aCompCor",
    "Retained": true,
    "SingularValue": 52.9744395794,
    "VarianceExplained": 0.0051032756
  },
  "w_comp_cor_50": {
    "CumulativeVarianceExplained": 0.4295286614,
    "Mask": "WM",
    "Method": "aCompCor",
    "Retained": true,
    "SingularValue": 52.4814539627,
    "VarianceExplained": 0.0050087343
  },
  "w_comp_cor_51": {
    "CumulativeVarianceExplained": 0.4345178515,
    "Mask": "WM",
    "Method": "aCompCor",
    "Retained": true,
    "SingularValue": 52.3789619253,
    "VarianceExplained": 0.0049891901
  },
  "w_comp_cor_52": {
    "CumulativeVarianceExplained": 0.4394462787,
    "Mask": "WM",
    "Method": "aCompCor",
    "Retained": true,
    "SingularValue": 52.0590249266,
    "VarianceExplained": 0.0049284271
  },
  "w_comp_cor_53": {
    "CumulativeVarianceExplained": 0.4443276975,
    "Mask": "WM",
    "Method": "aCompCor",
    "Retained": true,
    "SingularValue": 51.8101557536,
    "VarianceExplained": 0.0048814189
  },
  "w_comp_cor_54": {
    "CumulativeVarianceExplained": 0.4491913178,
    "Mask": "WM",
    "Method": "aCompCor",
    "Retained": true,
    "SingularValue": 51.7156145628,
    "VarianceExplained": 0.0048636203
  },
  "w_comp_cor_55": {
    "CumulativeVarianceExplained": 0.4540004689,
    "Mask": "WM",
    "Method": "aCompCor",
    "Retained": true,
    "SingularValue": 51.4252095148,
    "VarianceExplained": 0.0048091511
  },
  "w_comp_cor_56": {
    "CumulativeVarianceExplained": 0.4587525135,
    "Mask": "WM",
    "Method": "aCompCor",
    "Retained": true,
    "SingularValue": 51.1189724553,
    "VarianceExplained": 0.0047520446
  },
  "w_comp_cor_57": {
    "CumulativeVarianceExplained": 0.4634965682,
    "Mask": "WM",
    "Method": "aCompCor",
    "Retained": true,
    "SingularValue": 51.0759791311,
    "VarianceExplained": 0.0047440546
  },
  "w_comp_cor_58": {
    "CumulativeVarianceExplained": 0.4681706533,
    "Mask": "WM",
    "Method": "aCompCor",
    "Retained": true,
    "SingularValue": 50.6979234361,
    "VarianceExplained": 0.0046740852
  },
  "w_comp_cor_59": {
    "CumulativeVarianceExplained": 0.4727591947,
    "Mask": "WM",
    "Method": "aCompCor",
    "Retained": true,
    "SingularValue": 50.2318512718,
    "VarianceExplained": 0.0045885413
  },
  "w_comp_cor_60": {
    "CumulativeVarianceExplained": 0.4773260674,
    "Mask": "WM",
    "Method": "aCompCor",
    "Retained": true,
    "SingularValue": 50.1131050175,
    "VarianceExplained": 0.0045668727
  },
  "w_comp_cor_61": {
    "CumulativeVarianceExplained": 0.4818458149,
    "Mask": "WM",
    "Method": "aCompCor",
    "Retained": true,
    "SingularValue": 49.853878138,
    "VarianceExplained": 0.0045197475
  },
  "w_comp_cor_62": {
    "CumulativeVarianceExplained": 0.4863158551,
    "Mask": "WM",
    "Method": "aCompCor",
    "Retained": true,
    "SingularValue": 49.5789783304,
    "VarianceExplained": 0.0044700402
  },
  "w_comp_cor_63": {
    "CumulativeVarianceExplained": 0.4907596529,
    "Mask": "WM",
    "Method": "aCompCor",
    "Retained": true,
    "SingularValue": 49.4332320953,
    "VarianceExplained": 0.0044437978
  },
  "w_comp_cor_64": {
    "CumulativeVarianceExplained": 0.4951935512,
    "Mask": "WM",
    "Method": "aCompCor",
    "Retained": true,
    "SingularValue": 49.3781395929,
    "VarianceExplained": 0.0044338983
  },
  "w_comp_cor_65": {
    "CumulativeVarianceExplained": 0.4995739458,
    "Mask": "WM",
    "Method": "aCompCor",
    "Retained": true,
    "SingularValue": 49.0793130766,
    "VarianceExplained": 0.0043803946
  },
  "w_comp_cor_66": {
    "CumulativeVarianceExplained": 0.5039169099,
    "Mask": "WM",
    "Method": "aCompCor",
    "Retained": true,
    "SingularValue": 48.8691722181,
    "VarianceExplained": 0.0043429642
  }
}